{"2315":{"code":"2315","kind":"CRS-PROJCRS","name":"Campo Inchauspe / UTM zone 19S","wkt":"PROJCRS[\"Campo Inchauspe / UTM zone 19S\",BASEGEOGCRS[\"Campo Inchauspe\",DATUM[\"Campo Inchauspe\",ELLIPSOID[\"International 1924\",6378388,297,LENGTHUNIT[\"metre\",1,ID[\"EPSG\",9001]],ID[\"EPSG\",7022]],ID[\"EPSG\",6221]],ID[\"EPSG\",4221]],CONVERSION[\"UTM zone 19S\",METHOD[\"Transverse Mercator\",ID[\"EPSG\",9807]],PARAMETER[\"Latitude of natural origin\",0,ANGLEUNIT[\"degree\",0.0174532925199433,ID[\"EPSG\",9102]],ID[\"EPSG\",8801]],PARAMETER[\"Longitude of natural origin\",-69,ANGLEUNIT[\"degree\",0.0174532925199433,ID[\"EPSG\",9102]],ID[\"EPSG\",8802]],PARAMETER[\"Scale factor at natural origin\",0.9996,SCALEUNIT[\"unity\",1,ID[\"EPSG\",9201]],ID[\"EPSG\",8805]],PARAMETER[\"False easting\",500000,LENGTHUNIT[\"metre\",1,ID[\"EPSG\",9001]],ID[\"EPSG\",8806]],PARAMETER[\"False northing\",10000000,LENGTHUNIT[\"metre\",1,ID[\"EPSG\",9001]],ID[\"EPSG\",8807]],ID[\"EPSG\",16119]],CS[Cartesian,2,ID[\"EPSG\",4400]],AXIS[\"Easting (E)\",east],AXIS[\"Northing (N)\",north],LENGTHUNIT[\"metre\",1,ID[\"EPSG\",9001]],ID[\"EPSG\",2315]]","proj4":"+proj=utm +zone=19 +south +ellps=intl +towgs84=-148,136,90,0,0,0,0 +units=m +no_defs +type=crs","bbox":[-51.65,-68.62,-54.61,-66],"unit":"metre","accuracy":9},"3315":{"accuracy":1,"authority":"EPSG","bbox":[-4.99,21.74,-13.46,30.78],"code":"3315","default_trans":4068,"kind":"CRS-PROJCRS","name":"Katanga 1955 / Katanga TM","proj4":"+proj=tmerc +lat_0=-9 +lon_0=26 +k=0.9998 +x_0=0 +y_0=0 +ellps=clrk66 +towgs84=-102.283,-10.277,-257.396,-3.976,-0.002,-6.203,12.315 +units=m +no_defs +type=crs","trans":[4065,4066,4067,4068],"unit":"metre","wkt":"PROJCS[\"Katanga 1955 / Katanga TM\",GEOGCS[\"Katanga 1955\",DATUM[\"Katanga_1955\",SPHEROID[\"Clarke 1866\",6378206.4,294.978698213898],TOWGS84[-102.283,-10.277,-257.396,-3.976,-0.002,-6.203,12.315]],PRIMEM[\"Greenwich\",0,AUTHORITY[\"EPSG\",\"8901\"]],UNIT[\"degree\",0.0174532925199433,AUTHORITY[\"EPSG\",\"9122\"]],AUTHORITY[\"EPSG\",\"4695\"]],PROJECTION[\"Transverse_Mercator\"],PARAMETER[\"latitude_of_origin\",-9],PARAMETER[\"central_meridian\",26],PARAMETER[\"scale_factor\",0.9998],PARAMETER[\"false_easting\",0],PARAMETER[\"false_northing\",0],UNIT[\"metre\",1,AUTHORITY[\"EPSG\",\"9001\"]],AXIS[\"Easting\",EAST],AXIS[\"Northing\",NORTH],AUTHORITY[\"EPSG\",\"3315\"]]"},"4315":{"code":"4315","kind":"CRS-GEOGCRS","name":"Conakry 1905","wkt":"GEOGCRS[\"Conakry 1905\",DATUM[\"Conakry 1905\",ELLIPSOID[\"Clarke 1880 (IGN)\",6378249.2,293.466021293627,LENGTHUNIT[\"metre\",1,ID[\"EPSG\",9001]],ID[\"EPSG\",7011]],ID[\"EPSG\",6315]],CS[ellipsoidal,2,ID[\"EPSG\",6422]],AXIS[\"Geodetic latitude (Lat)\",north],AXIS[\"Geodetic longitude (Lon)\",east],ANGLEUNIT[\"degree\",0.0174532925199433,ID[\"EPSG\",9102]],ID[\"EPSG\",4315]]","proj4":"+proj=longlat +ellps=clrk80ign +towgs84=-23,259,-9,0,0,0,0 +no_defs +type=crs +axis=neu","bbox":[12.68,-15.13,7.19,-7.65],"unit":"degree (supplier to define representation)","accuracy":30},"7315":{"code":"7315","kind":"CRS-PROJCRS","name":"NAD83(2011) / InGCS Huntington-Whitley (m)","wkt":"PROJCRS[\"NAD83(2011) / InGCS Huntington-Whitley (m)\",BASEGEOGCRS[\"NAD83(2011)\",DATUM[\"NAD83 (National Spatial Reference System 2011)\",ELLIPSOID[\"GRS 1980\",6378137,298.257222101,LENGTHUNIT[\"metre\",1,ID[\"EPSG\",9001]],ID[\"EPSG\",7019]], ANCHOREPOCH[2010],ID[\"EPSG\",1116]],ID[\"EPSG\",6318]],CONVERSION[\"InGCS Huntington-Whitley (m)\",METHOD[\"Transverse Mercator\",ID[\"EPSG\",9807]],PARAMETER[\"Latitude of natural origin\",40.6500000000003,ANGLEUNIT[\"degree\",0.0174532925199433,ID[\"EPSG\",9102]],ID[\"EPSG\",8801]],PARAMETER[\"Longitude of natural origin\",-85.5000000000003,ANGLEUNIT[\"degree\",0.0174532925199433,ID[\"EPSG\",9102]],ID[\"EPSG\",8802]],PARAMETER[\"Scale factor at natural origin\",1.000034,SCALEUNIT[\"unity\",1,ID[\"EPSG\",9201]],ID[\"EPSG\",8805]],PARAMETER[\"False easting\",240000,LENGTHUNIT[\"metre\",1,ID[\"EPSG\",9001]],ID[\"EPSG\",8806]],PARAMETER[\"False northing\",36000,LENGTHUNIT[\"metre\",1,ID[\"EPSG\",9001]],ID[\"EPSG\",8807]],ID[\"EPSG\",7201]],CS[Cartesian,2,ID[\"EPSG\",4499]],AXIS[\"Easting (X)\",east],AXIS[\"Northing (Y)\",north],LENGTHUNIT[\"metre\",1,ID[\"EPSG\",9001]],ID[\"EPSG\",7315]]","proj4":"+proj=tmerc +lat_0=40.65 +lon_0=-85.5 +k=1.000034 +x_0=240000 +y_0=36000 +ellps=GRS80 +towgs84=0,0,0,0,0,0,0 +units=m +no_defs +type=crs","bbox":[41.3,-85.69,40.65,-85.3],"unit":"metre","accuracy":2},"8315":{"code":"8315","kind":"CRS-PROJCRS","name":"NAD83(2011) / Oregon Coast Range North zone (m)","wkt":"PROJCRS[\"NAD83(2011) / Oregon Coast Range North zone (m)\",BASEGEOGCRS[\"NAD83(2011)\",DATUM[\"NAD83 (National Spatial Reference System 2011)\",ELLIPSOID[\"GRS 1980\",6378137,298.257222101,LENGTHUNIT[\"metre\",1,ID[\"EPSG\",9001]],ID[\"EPSG\",7019]], ANCHOREPOCH[2010],ID[\"EPSG\",1116]],ID[\"EPSG\",6318]],CONVERSION[\"Oregon Coast Range North zone (meter)\",METHOD[\"Lambert Conic Conformal (1SP)\",ID[\"EPSG\",9801]],PARAMETER[\"Latitude of natural origin\",45.5833333333336,ANGLEUNIT[\"degree\",0.0174532925199433,ID[\"EPSG\",9102]],ID[\"EPSG\",8801]],PARAMETER[\"Longitude of natural origin\",-123.416666666667,ANGLEUNIT[\"degree\",0.0174532925199433,ID[\"EPSG\",9102]],ID[\"EPSG\",8802]],PARAMETER[\"Scale factor at natural origin\",1.000045,SCALEUNIT[\"unity\",1,ID[\"EPSG\",9201]],ID[\"EPSG\",8805]],PARAMETER[\"False easting\",30000,LENGTHUNIT[\"metre\",1,ID[\"EPSG\",9001]],ID[\"EPSG\",8806]],PARAMETER[\"False northing\",20000,LENGTHUNIT[\"metre\",1,ID[\"EPSG\",9001]],ID[\"EPSG\",8807]],ID[\"EPSG\",8277]],CS[Cartesian,2,ID[\"EPSG\",4499]],AXIS[\"Easting (X)\",east],AXIS[\"Northing (Y)\",north],LENGTHUNIT[\"metre\",1,ID[\"EPSG\",9001]],ID[\"EPSG\",8315]]","proj4":"+proj=lcc +lat_1=45.5833333333333 +lat_0=45.5833333333333 +lon_0=-123.416666666667 +k_0=1.000045 +x_0=30000 +y_0=20000 +ellps=GRS80 +towgs84=0,0,0,0,0,0,0 +units=m +no_defs +type=crs","bbox":[45.98,-123.81,45.4,-123.01],"unit":"metre","accuracy":2},"21315":{"code":"21315","kind":"CRS-PROJCRS","name":"GSK-2011 / GSK 3GK CM 45E","wkt":"PROJCRS[\"GSK-2011 / GSK 3GK CM 45E\",BASEGEOGCRS[\"GSK-2011\",DATUM[\"Geodezicheskaya Sistema Koordinat 2011\",ELLIPSOID[\"GSK-2011\",6378136.5,298.2564151,LENGTHUNIT[\"metre\",1,ID[\"EPSG\",9001]],ID[\"EPSG\",1025]],ID[\"EPSG\",1159]],ID[\"EPSG\",7683]],CONVERSION[\"GSK 3-degree Gauss-Kruger CM 45E\",METHOD[\"Transverse Mercator\",ID[\"EPSG\",9807]],PARAMETER[\"Latitude of natural origin\",0,ANGLEUNIT[\"degree\",0.0174532925199433,ID[\"EPSG\",9102]],ID[\"EPSG\",8801]],PARAMETER[\"Longitude of natural origin\",45,ANGLEUNIT[\"degree\",0.0174532925199433,ID[\"EPSG\",9102]],ID[\"EPSG\",8802]],PARAMETER[\"Scale factor at natural origin\",1,SCALEUNIT[\"unity\",1,ID[\"EPSG\",9201]],ID[\"EPSG\",8805]],PARAMETER[\"False easting\",250000,LENGTHUNIT[\"metre\",1,ID[\"EPSG\",9001]],ID[\"EPSG\",8806]],PARAMETER[\"False northing\",0,LENGTHUNIT[\"metre\",1,ID[\"EPSG\",9001]],ID[\"EPSG\",8807]],ID[\"EPSG\",17115]],CS[Cartesian,2,ID[\"EPSG\",4530]],AXIS[\"Northing (X)\",north],AXIS[\"Easting (Y)\",east],LENGTHUNIT[\"metre\",1,ID[\"EPSG\",9001]],ID[\"EPSG\",21315]]","proj4":"+proj=tmerc +lat_0=0 +lon_0=45 +k=1 +x_0=250000 +y_0=0 +ellps=GSK2011 +towgs84=0,0,0,0,0,0,0 +units=m +no_defs +type=crs +axis=neu","bbox":[80.8,43.5,41.89,46.5],"unit":"metre","accuracy":1},"22315":{"code":"22315","kind":"CRS-PROJCRS","name":"NAD83(CSRS)v3 / UTM zone 15N","wkt":"PROJCRS[\"NAD83(CSRS)v3 / UTM zone 15N\",BASEGEOGCRS[\"NAD83(CSRS)v3\",DATUM[\"North American Datum of 1983 (CSRS) version 3\",ELLIPSOID[\"GRS 1980\",6378137,298.257222101,LENGTHUNIT[\"metre\",1,ID[\"EPSG\",9001]],ID[\"EPSG\",7019]], ANCHOREPOCH[1997],ID[\"EPSG\",1194]],ID[\"EPSG\",8240]],CONVERSION[\"UTM zone 15N\",METHOD[\"Transverse Mercator\",ID[\"EPSG\",9807]],PARAMETER[\"Latitude of natural origin\",0,ANGLEUNIT[\"degree\",0.0174532925199433,ID[\"EPSG\",9102]],ID[\"EPSG\",8801]],PARAMETER[\"Longitude of natural origin\",-93,ANGLEUNIT[\"degree\",0.0174532925199433,ID[\"EPSG\",9102]],ID[\"EPSG\",8802]],PARAMETER[\"Scale factor at natural origin\",0.9996,SCALEUNIT[\"unity\",1,ID[\"EPSG\",9201]],ID[\"EPSG\",8805]],PARAMETER[\"False easting\",500000,LENGTHUNIT[\"metre\",1,ID[\"EPSG\",9001]],ID[\"EPSG\",8806]],PARAMETER[\"False northing\",0,LENGTHUNIT[\"metre\",1,ID[\"EPSG\",9001]],ID[\"EPSG\",8807]],ID[\"EPSG\",16015]],CS[Cartesian,2,ID[\"EPSG\",4400]],AXIS[\"Easting (E)\",east],AXIS[\"Northing (N)\",north],LENGTHUNIT[\"metre\",1,ID[\"EPSG\",9001]],ID[\"EPSG\",22315]]","proj4":"+proj=utm +zone=15 +ellps=GRS80 +units=m +no_defs +type=crs","bbox":[84,-96,48.03,-90],"unit":"metre","accuracy":null},"32315":{"code":"32315","kind":"CRS-PROJCRS","name":"WGS 72 / UTM zone 15S","wkt":"PROJCRS[\"WGS 72 / UTM zone 15S\",BASEGEOGCRS[\"WGS 72\", DYNAMIC[FRAMEEPOCH[1972.0]],DATUM[\"World Geodetic System 1972\",ELLIPSOID[\"WGS 72\",6378135,298.26,LENGTHUNIT[\"metre\",1,ID[\"EPSG\",9001]],ID[\"EPSG\",7043]],ID[\"EPSG\",6322]],ID[\"EPSG\",4322]],CONVERSION[\"UTM zone 15S\",METHOD[\"Transverse Mercator\",ID[\"EPSG\",9807]],PARAMETER[\"Latitude of natural origin\",0,ANGLEUNIT[\"degree\",0.0174532925199433,ID[\"EPSG\",9102]],ID[\"EPSG\",8801]],PARAMETER[\"Longitude of natural origin\",-93,ANGLEUNIT[\"degree\",0.0174532925199433,ID[\"EPSG\",9102]],ID[\"EPSG\",8802]],PARAMETER[\"Scale factor at natural origin\",0.9996,SCALEUNIT[\"unity\",1,ID[\"EPSG\",9201]],ID[\"EPSG\",8805]],PARAMETER[\"False easting\",500000,LENGTHUNIT[\"metre\",1,ID[\"EPSG\",9001]],ID[\"EPSG\",8806]],PARAMETER[\"False northing\",10000000,LENGTHUNIT[\"metre\",1,ID[\"EPSG\",9001]],ID[\"EPSG\",8807]],ID[\"EPSG\",16115]],CS[Cartesian,2,ID[\"EPSG\",4400]],AXIS[\"Easting (E)\",east],AXIS[\"Northing (N)\",north],LENGTHUNIT[\"metre\",1,ID[\"EPSG\",9001]],ID[\"EPSG\",32315]]","proj4":"+proj=utm +zone=15 +south +ellps=WGS72 +towgs84=0,0,4.5,0,0,0.554,0.219 +units=m +no_defs +type=crs","bbox":[0,-96,-80,-90],"unit":"metre","accuracy":2},"102315":{"accuracy":"","authority":"ESRI","bbox":[45.02,-75.87,40.88,-73.23],"code":"102315","default_trans":0,"kind":"CRS-PROJCRS","name":"NAD 1983 HARN SPCS New York East","proj4":"+proj=tmerc +lat_0=38.8333333333333 +lon_0=-74.5 +k=0.9999 +x_0=150000 +y_0=0 +ellps=GRS80 +units=m +no_defs +type=crs","trans":[],"unit":"","wkt":"PROJCS[\"NAD_1983_HARN_StatePlane_New_York_East_FIPS_3101 (deprecated)\",GEOGCS[\"NAD83(HARN)\",DATUM[\"NAD83_High_Accuracy_Reference_Network\",SPHEROID[\"GRS 1980\",6378137,298.257222101,AUTHORITY[\"EPSG\",\"7019\"]],AUTHORITY[\"EPSG\",\"6152\"]],PRIMEM[\"Greenwich\",0,AUTHORITY[\"EPSG\",\"8901\"]],UNIT[\"degree\",0.0174532925199433,AUTHORITY[\"EPSG\",\"9122\"]],AUTHORITY[\"EPSG\",\"4152\"]],PROJECTION[\"Transverse_Mercator\"],PARAMETER[\"latitude_of_origin\",38.8333333333333],PARAMETER[\"central_meridian\",-74.5],PARAMETER[\"scale_factor\",0.9999],PARAMETER[\"false_easting\",150000],PARAMETER[\"false_northing\",0],UNIT[\"metre\",1,AUTHORITY[\"EPSG\",\"9001\"]],AXIS[\"Easting\",EAST],AXIS[\"Northing\",NORTH],AUTHORITY[\"ESRI\",\"102315\"]]"},"103315":{"accuracy":"","authority":"ESRI","bbox":[47.31,-92.89,42.48,-86.25],"code":"103315","default_trans":0,"kind":"CRS-PROJCRS","name":"NAD 1983 HARN Wisconsin CRS Douglas (meters)","proj4":"+proj=tmerc +lat_0=45.8833333333333 +lon_0=-91.9166666666667 +k=1.0000385418 +x_0=59131.3183 +y_0=0.0041 +ellps=GRS80 +units=m +no_defs +type=crs","trans":[],"unit":"","wkt":"PROJCS[\"NAD_1983_HARN_WISCRS_Douglas_County_Meters (deprecated)\",GEOGCS[\"NAD83(HARN)\",DATUM[\"NAD83_High_Accuracy_Reference_Network\",SPHEROID[\"GRS 1980\",6378137,298.257222101,AUTHORITY[\"EPSG\",\"7019\"]],AUTHORITY[\"EPSG\",\"6152\"]],PRIMEM[\"Greenwich\",0,AUTHORITY[\"EPSG\",\"8901\"]],UNIT[\"degree\",0.0174532925199433,AUTHORITY[\"EPSG\",\"9122\"]],AUTHORITY[\"EPSG\",\"4152\"]],PROJECTION[\"Transverse_Mercator\"],PARAMETER[\"latitude_of_origin\",45.8833333333333],PARAMETER[\"central_meridian\",-91.9166666666667],PARAMETER[\"scale_factor\",1.0000385418],PARAMETER[\"false_easting\",59131.3183],PARAMETER[\"false_northing\",0.0041],UNIT[\"metre\",1,AUTHORITY[\"EPSG\",\"9001\"]],AXIS[\"Easting\",EAST],AXIS[\"Northing\",NORTH],AUTHORITY[\"ESRI\",\"103315\"]]"}}