{"2467":{"code":"2467","kind":"CRS-PROJCRS","name":"Pulkovo 1995 / Gauss-Kruger CM 45E","wkt":"PROJCRS[\"Pulkovo 1995 / Gauss-Kruger CM 45E\",BASEGEOGCRS[\"Pulkovo 1995\",DATUM[\"Pulkovo 1995\",ELLIPSOID[\"Krassowsky 1940\",6378245,298.3,LENGTHUNIT[\"metre\",1,ID[\"EPSG\",9001]],ID[\"EPSG\",7024]],ID[\"EPSG\",6200]],ID[\"EPSG\",4200]],CONVERSION[\"Gauss-Kruger CM 45E\",METHOD[\"Transverse Mercator\",ID[\"EPSG\",9807]],PARAMETER[\"Latitude of natural origin\",0,ANGLEUNIT[\"degree\",0.0174532925199433,ID[\"EPSG\",9102]],ID[\"EPSG\",8801]],PARAMETER[\"Longitude of natural origin\",45,ANGLEUNIT[\"degree\",0.0174532925199433,ID[\"EPSG\",9102]],ID[\"EPSG\",8802]],PARAMETER[\"Scale factor at natural origin\",1,SCALEUNIT[\"unity\",1,ID[\"EPSG\",9201]],ID[\"EPSG\",8805]],PARAMETER[\"False easting\",500000,LENGTHUNIT[\"metre\",1,ID[\"EPSG\",9001]],ID[\"EPSG\",8806]],PARAMETER[\"False northing\",0,LENGTHUNIT[\"metre\",1,ID[\"EPSG\",9001]],ID[\"EPSG\",8807]],ID[\"EPSG\",16308]],CS[Cartesian,2,ID[\"EPSG\",4530]],AXIS[\"Northing (X)\",north],AXIS[\"Easting (Y)\",east],LENGTHUNIT[\"metre\",1,ID[\"EPSG\",9001]],ID[\"EPSG\",2467]]","proj4":"+proj=tmerc +lat_0=0 +lon_0=45 +k=1 +x_0=500000 +y_0=0 +ellps=krass +towgs84=24.47,-130.89,-81.56,0,0,-0.13,-0.22 +units=m +no_defs +type=crs +axis=neu","bbox":[80.91,42,41.19,48],"unit":"metre","accuracy":1},"3467":{"code":"3467","kind":"CRS-PROJCRS","name":"NAD83(NSRS2007) / Alaska Albers","wkt":"PROJCRS[\"NAD83(NSRS2007) / Alaska Albers\",BASEGEOGCRS[\"NAD83(NSRS2007)\",DATUM[\"NAD83 (National Spatial Reference System 2007)\",ELLIPSOID[\"GRS 1980\",6378137,298.257222101,LENGTHUNIT[\"metre\",1,ID[\"EPSG\",9001]],ID[\"EPSG\",7019]],ID[\"EPSG\",6759]],ID[\"EPSG\",4759]],CONVERSION[\"Alaska Albers (meter)\",METHOD[\"Albers Equal Area\",ID[\"EPSG\",9822]],PARAMETER[\"Latitude of false origin\",50,ANGLEUNIT[\"degree\",0.0174532925199433,ID[\"EPSG\",9102]],ID[\"EPSG\",8821]],PARAMETER[\"Longitude of false origin\",-154,ANGLEUNIT[\"degree\",0.0174532925199433,ID[\"EPSG\",9102]],ID[\"EPSG\",8822]],PARAMETER[\"Latitude of 1st standard parallel\",55,ANGLEUNIT[\"degree\",0.0174532925199433,ID[\"EPSG\",9102]],ID[\"EPSG\",8823]],PARAMETER[\"Latitude of 2nd standard parallel\",65,ANGLEUNIT[\"degree\",0.0174532925199433,ID[\"EPSG\",9102]],ID[\"EPSG\",8824]],PARAMETER[\"Easting at false origin\",0,LENGTHUNIT[\"metre\",1,ID[\"EPSG\",9001]],ID[\"EPSG\",8826]],PARAMETER[\"Northing at false origin\",0,LENGTHUNIT[\"metre\",1,ID[\"EPSG\",9001]],ID[\"EPSG\",8827]],ID[\"EPSG\",15021]],CS[Cartesian,2,ID[\"EPSG\",4499]],AXIS[\"Easting (X)\",east],AXIS[\"Northing (Y)\",north],LENGTHUNIT[\"metre\",1,ID[\"EPSG\",9001]],ID[\"EPSG\",3467]]","proj4":"+proj=aea +lat_0=50 +lon_0=-154 +lat_1=55 +lat_2=65 +x_0=0 +y_0=0 +ellps=GRS80 +towgs84=0,0,0,0,0,0,0 +units=m +no_defs +type=crs","bbox":[71.4,172.42,51.3,-129.99],"unit":"metre","accuracy":2},"4467":{"code":"4467","kind":"CRS-PROJCRS","name":"RGSPM06 / UTM zone 21N","wkt":"PROJCRS[\"RGSPM06 / UTM zone 21N\",BASEGEOGCRS[\"RGSPM06\",DATUM[\"Reseau Geodesique de Saint Pierre et Miquelon 2006\",ELLIPSOID[\"GRS 1980\",6378137,298.257222101,LENGTHUNIT[\"metre\",1,ID[\"EPSG\",9001]],ID[\"EPSG\",7019]],ID[\"EPSG\",1038]],ID[\"EPSG\",4463]],CONVERSION[\"UTM zone 21N\",METHOD[\"Transverse Mercator\",ID[\"EPSG\",9807]],PARAMETER[\"Latitude of natural origin\",0,ANGLEUNIT[\"degree\",0.0174532925199433,ID[\"EPSG\",9102]],ID[\"EPSG\",8801]],PARAMETER[\"Longitude of natural origin\",-57,ANGLEUNIT[\"degree\",0.0174532925199433,ID[\"EPSG\",9102]],ID[\"EPSG\",8802]],PARAMETER[\"Scale factor at natural origin\",0.9996,SCALEUNIT[\"unity\",1,ID[\"EPSG\",9201]],ID[\"EPSG\",8805]],PARAMETER[\"False easting\",500000,LENGTHUNIT[\"metre\",1,ID[\"EPSG\",9001]],ID[\"EPSG\",8806]],PARAMETER[\"False northing\",0,LENGTHUNIT[\"metre\",1,ID[\"EPSG\",9001]],ID[\"EPSG\",8807]],ID[\"EPSG\",16021]],CS[Cartesian,2,ID[\"EPSG\",4400]],AXIS[\"Easting (E)\",east],AXIS[\"Northing (N)\",north],LENGTHUNIT[\"metre\",1,ID[\"EPSG\",9001]],ID[\"EPSG\",4467]]","proj4":"+proj=utm +zone=21 +ellps=GRS80 +towgs84=0,0,0,0,0,0,0 +units=m +no_defs +type=crs","bbox":[47.37,-57.1,43.41,-55.9],"unit":"metre","accuracy":1},"5467":{"code":"5467","kind":"CRS-GEOGCRS","name":"Panama-Colon 1911","wkt":"GEOGCRS[\"Panama-Colon 1911\",DATUM[\"Panama-Colon 1911\",ELLIPSOID[\"Clarke 1866\",6378206.4,294.978698213901,LENGTHUNIT[\"metre\",1,ID[\"EPSG\",9001]],ID[\"EPSG\",7008]],ID[\"EPSG\",1072]],CS[ellipsoidal,2,ID[\"EPSG\",6422]],AXIS[\"Geodetic latitude (Lat)\",north],AXIS[\"Geodetic longitude (Lon)\",east],ANGLEUNIT[\"degree\",0.0174532925199433,ID[\"EPSG\",9102]],ID[\"EPSG\",5467]]","proj4":"+proj=longlat +ellps=clrk66 +no_defs +type=crs +axis=neu","bbox":[9.68,-83.04,7.15,-77.19],"unit":"degree (supplier to define representation)","accuracy":null},"6467":{"code":"6467","kind":"CRS-PROJCRS","name":"NAD83(2011) / Kansas North (ftUS)","wkt":"PROJCRS[\"NAD83(2011) / Kansas North (ftUS)\",BASEGEOGCRS[\"NAD83(2011)\",DATUM[\"NAD83 (National Spatial Reference System 2011)\",ELLIPSOID[\"GRS 1980\",6378137,298.257222101,LENGTHUNIT[\"metre\",1,ID[\"EPSG\",9001]],ID[\"EPSG\",7019]], ANCHOREPOCH[2010],ID[\"EPSG\",1116]],ID[\"EPSG\",6318]],CONVERSION[\"SPCS83 Kansas North zone (US survey foot)\",METHOD[\"Lambert Conic Conformal (2SP)\",ID[\"EPSG\",9802]],PARAMETER[\"Latitude of false origin\",38.3333333333336,ANGLEUNIT[\"degree\",0.0174532925199433,ID[\"EPSG\",9102]],ID[\"EPSG\",8821]],PARAMETER[\"Longitude of false origin\",-98,ANGLEUNIT[\"degree\",0.0174532925199433,ID[\"EPSG\",9102]],ID[\"EPSG\",8822]],PARAMETER[\"Latitude of 1st standard parallel\",39.7833333333336,ANGLEUNIT[\"degree\",0.0174532925199433,ID[\"EPSG\",9102]],ID[\"EPSG\",8823]],PARAMETER[\"Latitude of 2nd standard parallel\",38.7166666666669,ANGLEUNIT[\"degree\",0.0174532925199433,ID[\"EPSG\",9102]],ID[\"EPSG\",8824]],PARAMETER[\"Easting at false origin\",1312333.3333,LENGTHUNIT[\"US survey foot\",0.304800609601219,ID[\"EPSG\",9003]],ID[\"EPSG\",8826]],PARAMETER[\"Northing at false origin\",0,LENGTHUNIT[\"US survey foot\",0.304800609601219,ID[\"EPSG\",9003]],ID[\"EPSG\",8827]],ID[\"EPSG\",15379]],CS[Cartesian,2,ID[\"EPSG\",4497]],AXIS[\"Easting (X)\",east],AXIS[\"Northing (Y)\",north],LENGTHUNIT[\"US survey foot\",0.304800609601219,ID[\"EPSG\",9003]],ID[\"EPSG\",6467]]","proj4":"+proj=lcc +lat_0=38.3333333333333 +lon_0=-98 +lat_1=39.7833333333333 +lat_2=38.7166666666667 +x_0=399999.99998984 +y_0=0 +ellps=GRS80 +towgs84=0,0,0,0,0,0,0 +units=us-ft +no_defs +type=crs","bbox":[40.01,-102.06,38.52,-94.58],"unit":"US survey foot","accuracy":2},"28467":{"accuracy":4.5,"authority":"EPSG","bbox":[69.23,36,41.43,42],"code":"28467","default_trans":15865,"kind":"CRS-PROJCRS","name":"Pulkovo 1942 / Gauss-Kruger 7N","proj4":"+proj=tmerc +lat_0=0 +lon_0=39 +k=1 +x_0=500000 +y_0=0 +ellps=krass +towgs84=25,-141,-78.5,0,-0.35,-0.736,0 +units=m +no_defs +type=crs","trans":[1254,1267,1274,1287,1288,1289,1290,1291,1292,1293,1303,1310,1332,1334,1679,1807,1808,1809,5044,5586,6899,8199,8236,8658,15844,15865],"unit":"metre","wkt":"PROJCS[\"Pulkovo 1942 / Gauss-Kruger 7N\",GEOGCS[\"Pulkovo 1942\",DATUM[\"Pulkovo_1942\",SPHEROID[\"Krassowsky 1940\",6378245,298.3],TOWGS84[25,-141,-78.5,0,-0.35,-0.736,0]],PRIMEM[\"Greenwich\",0,AUTHORITY[\"EPSG\",\"8901\"]],UNIT[\"degree\",0.0174532925199433,AUTHORITY[\"EPSG\",\"9122\"]],AUTHORITY[\"EPSG\",\"4284\"]],PROJECTION[\"Transverse_Mercator\"],PARAMETER[\"latitude_of_origin\",0],PARAMETER[\"central_meridian\",39],PARAMETER[\"scale_factor\",1],PARAMETER[\"false_easting\",500000],PARAMETER[\"false_northing\",0],UNIT[\"metre\",1,AUTHORITY[\"EPSG\",\"9001\"]],AUTHORITY[\"EPSG\",\"28467\"]]"},"31467":{"code":"31467","kind":"CRS-PROJCRS","name":"DHDN / 3-degree Gauss-Kruger zone 3","wkt":"PROJCRS[\"DHDN / 3-degree Gauss-Kruger zone 3\",BASEGEOGCRS[\"DHDN\",DATUM[\"Deutsches Hauptdreiecksnetz\",ELLIPSOID[\"Bessel 1841\",6377397.155,299.1528128,LENGTHUNIT[\"metre\",1,ID[\"EPSG\",9001]],ID[\"EPSG\",7004]],ID[\"EPSG\",6314]],ID[\"EPSG\",4314]],CONVERSION[\"3-degree Gauss-Kruger zone 3\",METHOD[\"Transverse Mercator\",ID[\"EPSG\",9807]],PARAMETER[\"Latitude of natural origin\",0,ANGLEUNIT[\"degree\",0.0174532925199433,ID[\"EPSG\",9102]],ID[\"EPSG\",8801]],PARAMETER[\"Longitude of natural origin\",9,ANGLEUNIT[\"degree\",0.0174532925199433,ID[\"EPSG\",9102]],ID[\"EPSG\",8802]],PARAMETER[\"Scale factor at natural origin\",1,SCALEUNIT[\"unity\",1,ID[\"EPSG\",9201]],ID[\"EPSG\",8805]],PARAMETER[\"False easting\",3500000,LENGTHUNIT[\"metre\",1,ID[\"EPSG\",9001]],ID[\"EPSG\",8806]],PARAMETER[\"False northing\",0,LENGTHUNIT[\"metre\",1,ID[\"EPSG\",9001]],ID[\"EPSG\",8807]],ID[\"EPSG\",16263]],CS[Cartesian,2,ID[\"EPSG\",4530]],AXIS[\"Northing (X)\",north],AXIS[\"Easting (Y)\",east],LENGTHUNIT[\"metre\",1,ID[\"EPSG\",9001]],ID[\"EPSG\",31467]]","proj4":"+proj=tmerc +lat_0=0 +lon_0=9 +k=1 +x_0=3500000 +y_0=0 +ellps=bessel +nadgrids=BETA2007.gsb +units=m +no_defs +type=crs +axis=neu","bbox":[55.09,7.5,47.27,10.51],"unit":"metre","accuracy":1},"102467":{"accuracy":"","authority":"ESRI","bbox":[47.48,-96.86,45.28,-92.29],"code":"102467","default_trans":0,"kind":"CRS-PROJCRS","name":"NAD 1983 HARN SPCS Minnesota Central (US Feet)","proj4":"+proj=lcc +lat_0=45 +lon_0=-94.25 +lat_1=45.6166666666667 +lat_2=47.05 +x_0=800000.000000001 +y_0=100000 +ellps=GRS80 +units=us-ft +no_defs +type=crs","trans":[],"unit":"","wkt":"PROJCS[\"NAD_1983_HARN_StatePlane_Minnesota_Central_FIPS_2202_Feet (deprecated)\",GEOGCS[\"NAD83(HARN)\",DATUM[\"NAD83_High_Accuracy_Reference_Network\",SPHEROID[\"GRS 1980\",6378137,298.257222101,AUTHORITY[\"EPSG\",\"7019\"]],AUTHORITY[\"EPSG\",\"6152\"]],PRIMEM[\"Greenwich\",0,AUTHORITY[\"EPSG\",\"8901\"]],UNIT[\"degree\",0.0174532925199433,AUTHORITY[\"EPSG\",\"9122\"]],AUTHORITY[\"EPSG\",\"4152\"]],PROJECTION[\"Lambert_Conformal_Conic_2SP\"],PARAMETER[\"latitude_of_origin\",45],PARAMETER[\"central_meridian\",-94.25],PARAMETER[\"standard_parallel_1\",45.6166666666667],PARAMETER[\"standard_parallel_2\",47.05],PARAMETER[\"false_easting\",2624666.66666667],PARAMETER[\"false_northing\",328083.333333333],UNIT[\"US survey foot\",0.304800609601219,AUTHORITY[\"EPSG\",\"9003\"]],AXIS[\"Easting\",EAST],AXIS[\"Northing\",NORTH],AUTHORITY[\"ESRI\",\"102467\"]]"},"103467":{"accuracy":"","authority":"ESRI","bbox":[47.31,-92.89,42.48,-86.25],"code":"103467","default_trans":0,"kind":"CRS-PROJCRS","name":"NAD 1983 HARN Wisconsin CRS Waukesha (US feet)","proj4":"+proj=tmerc +lat_0=42.5694444444444 +lon_0=-88.225 +k=1.0000346179 +x_0=208788.417881636 +y_0=0.00335280670561341 +ellps=GRS80 +units=us-ft +no_defs +type=crs","trans":[],"unit":"","wkt":"PROJCS[\"NAD_1983_HARN_WISCRS_Waukesha_County_Feet (deprecated)\",GEOGCS[\"NAD83(HARN)\",DATUM[\"NAD83_High_Accuracy_Reference_Network\",SPHEROID[\"GRS 1980\",6378137,298.257222101,AUTHORITY[\"EPSG\",\"7019\"]],AUTHORITY[\"EPSG\",\"6152\"]],PRIMEM[\"Greenwich\",0,AUTHORITY[\"EPSG\",\"8901\"]],UNIT[\"degree\",0.0174532925199433,AUTHORITY[\"EPSG\",\"9122\"]],AUTHORITY[\"EPSG\",\"4152\"]],PROJECTION[\"Transverse_Mercator\"],PARAMETER[\"latitude_of_origin\",42.5694444444444],PARAMETER[\"central_meridian\",-88.225],PARAMETER[\"scale_factor\",1.0000346179],PARAMETER[\"false_easting\",685000.001],PARAMETER[\"false_northing\",0.011],UNIT[\"US survey foot\",0.304800609601219,AUTHORITY[\"EPSG\",\"9003\"]],AXIS[\"Easting\",EAST],AXIS[\"Northing\",NORTH],AUTHORITY[\"ESRI\",\"103467\"]]"}}