{"2474":{"code":"2474","kind":"CRS-PROJCRS","name":"Pulkovo 1995 / Gauss-Kruger CM 87E","wkt":"PROJCRS[\"Pulkovo 1995 / Gauss-Kruger CM 87E\",BASEGEOGCRS[\"Pulkovo 1995\",DATUM[\"Pulkovo 1995\",ELLIPSOID[\"Krassowsky 1940\",6378245,298.3,LENGTHUNIT[\"metre\",1,ID[\"EPSG\",9001]],ID[\"EPSG\",7024]],ID[\"EPSG\",6200]],ID[\"EPSG\",4200]],CONVERSION[\"Gauss-Kruger CM 87E\",METHOD[\"Transverse Mercator\",ID[\"EPSG\",9807]],PARAMETER[\"Latitude of natural origin\",0,ANGLEUNIT[\"degree\",0.0174532925199433,ID[\"EPSG\",9102]],ID[\"EPSG\",8801]],PARAMETER[\"Longitude of natural origin\",87,ANGLEUNIT[\"degree\",0.0174532925199433,ID[\"EPSG\",9102]],ID[\"EPSG\",8802]],PARAMETER[\"Scale factor at natural origin\",1,SCALEUNIT[\"unity\",1,ID[\"EPSG\",9201]],ID[\"EPSG\",8805]],PARAMETER[\"False easting\",500000,LENGTHUNIT[\"metre\",1,ID[\"EPSG\",9001]],ID[\"EPSG\",8806]],PARAMETER[\"False northing\",0,LENGTHUNIT[\"metre\",1,ID[\"EPSG\",9001]],ID[\"EPSG\",8807]],ID[\"EPSG\",16315]],CS[Cartesian,2,ID[\"EPSG\",4530]],AXIS[\"Northing (X)\",north],AXIS[\"Easting (Y)\",east],LENGTHUNIT[\"metre\",1,ID[\"EPSG\",9001]],ID[\"EPSG\",2474]]","proj4":"+proj=tmerc +lat_0=0 +lon_0=87 +k=1 +x_0=500000 +y_0=0 +ellps=krass +towgs84=24.47,-130.89,-81.56,0,0,-0.13,-0.22 +units=m +no_defs +type=crs +axis=neu","bbox":[81.27,84,49.07,90],"unit":"metre","accuracy":1},"3474":{"code":"3474","kind":"CRS-PROJCRS","name":"NAD83(NSRS2007) / Alaska zone 7","wkt":"PROJCRS[\"NAD83(NSRS2007) / Alaska zone 7\",BASEGEOGCRS[\"NAD83(NSRS2007)\",DATUM[\"NAD83 (National Spatial Reference System 2007)\",ELLIPSOID[\"GRS 1980\",6378137,298.257222101,LENGTHUNIT[\"metre\",1,ID[\"EPSG\",9001]],ID[\"EPSG\",7019]],ID[\"EPSG\",6759]],ID[\"EPSG\",4759]],CONVERSION[\"SPCS83 Alaska zone 7 (meter)\",METHOD[\"Transverse Mercator\",ID[\"EPSG\",9807]],PARAMETER[\"Latitude of natural origin\",54,ANGLEUNIT[\"degree\",0.0174532925199433,ID[\"EPSG\",9102]],ID[\"EPSG\",8801]],PARAMETER[\"Longitude of natural origin\",-162,ANGLEUNIT[\"degree\",0.0174532925199433,ID[\"EPSG\",9102]],ID[\"EPSG\",8802]],PARAMETER[\"Scale factor at natural origin\",0.9999,SCALEUNIT[\"unity\",1,ID[\"EPSG\",9201]],ID[\"EPSG\",8805]],PARAMETER[\"False easting\",500000,LENGTHUNIT[\"metre\",1,ID[\"EPSG\",9001]],ID[\"EPSG\",8806]],PARAMETER[\"False northing\",0,LENGTHUNIT[\"metre\",1,ID[\"EPSG\",9001]],ID[\"EPSG\",8807]],ID[\"EPSG\",15037]],CS[Cartesian,2,ID[\"EPSG\",4499]],AXIS[\"Easting (X)\",east],AXIS[\"Northing (Y)\",north],LENGTHUNIT[\"metre\",1,ID[\"EPSG\",9001]],ID[\"EPSG\",3474]]","proj4":"+proj=tmerc +lat_0=54 +lon_0=-162 +k=0.9999 +x_0=500000 +y_0=0 +ellps=GRS80 +towgs84=0,0,0,0,0,0,0 +units=m +no_defs +type=crs","bbox":[70.74,-164.01,54.32,-160],"unit":"metre","accuracy":2},"4474":{"accuracy":10,"authority":"EPSG","bbox":[-12.61,44.98,-13.05,45.35],"code":"4474","default_trans":1916,"kind":"CRS-PROJCRS","name":"Cadastre 1997 / UTM zone 38S","proj4":"+proj=utm +zone=38 +south +ellps=intl +towgs84=-382,-59,-262,0,0,0,0 +units=m +no_defs +type=crs","trans":[1916,5888],"unit":"metre","wkt":"PROJCS[\"Cadastre 1997 / UTM zone 38S\",GEOGCS[\"Combani 1950\",DATUM[\"Combani_1950\",SPHEROID[\"International 1924\",6378388,297],TOWGS84[-382,-59,-262,0,0,0,0]],PRIMEM[\"Greenwich\",0,AUTHORITY[\"EPSG\",\"8901\"]],UNIT[\"degree\",0.0174532925199433,AUTHORITY[\"EPSG\",\"9122\"]],AUTHORITY[\"EPSG\",\"4632\"]],PROJECTION[\"Transverse_Mercator\"],PARAMETER[\"latitude_of_origin\",0],PARAMETER[\"central_meridian\",45],PARAMETER[\"scale_factor\",0.9996],PARAMETER[\"false_easting\",500000],PARAMETER[\"false_northing\",10000000],UNIT[\"metre\",1,AUTHORITY[\"EPSG\",\"9001\"]],AXIS[\"Easting\",EAST],AXIS[\"Northing\",NORTH],AUTHORITY[\"EPSG\",\"4474\"]]"},"6474":{"code":"6474","kind":"CRS-PROJCRS","name":"NAD83(2011) / Kentucky South","wkt":"PROJCRS[\"NAD83(2011) / Kentucky South\",BASEGEOGCRS[\"NAD83(2011)\",DATUM[\"NAD83 (National Spatial Reference System 2011)\",ELLIPSOID[\"GRS 1980\",6378137,298.257222101,LENGTHUNIT[\"metre\",1,ID[\"EPSG\",9001]],ID[\"EPSG\",7019]], ANCHOREPOCH[2010],ID[\"EPSG\",1116]],ID[\"EPSG\",6318]],CONVERSION[\"SPCS83 Kentucky South zone (meter)\",METHOD[\"Lambert Conic Conformal (2SP)\",ID[\"EPSG\",9802]],PARAMETER[\"Latitude of false origin\",36.3333333333336,ANGLEUNIT[\"degree\",0.0174532925199433,ID[\"EPSG\",9102]],ID[\"EPSG\",8821]],PARAMETER[\"Longitude of false origin\",-85.7500000000003,ANGLEUNIT[\"degree\",0.0174532925199433,ID[\"EPSG\",9102]],ID[\"EPSG\",8822]],PARAMETER[\"Latitude of 1st standard parallel\",37.9333333333336,ANGLEUNIT[\"degree\",0.0174532925199433,ID[\"EPSG\",9102]],ID[\"EPSG\",8823]],PARAMETER[\"Latitude of 2nd standard parallel\",36.7333333333336,ANGLEUNIT[\"degree\",0.0174532925199433,ID[\"EPSG\",9102]],ID[\"EPSG\",8824]],PARAMETER[\"Easting at false origin\",500000,LENGTHUNIT[\"metre\",1,ID[\"EPSG\",9001]],ID[\"EPSG\",8826]],PARAMETER[\"Northing at false origin\",500000,LENGTHUNIT[\"metre\",1,ID[\"EPSG\",9001]],ID[\"EPSG\",8827]],ID[\"EPSG\",11632]],CS[Cartesian,2,ID[\"EPSG\",4499]],AXIS[\"Easting (X)\",east],AXIS[\"Northing (Y)\",north],LENGTHUNIT[\"metre\",1,ID[\"EPSG\",9001]],ID[\"EPSG\",6474]]","proj4":"+proj=lcc +lat_0=36.3333333333333 +lon_0=-85.75 +lat_1=37.9333333333333 +lat_2=36.7333333333333 +x_0=500000 +y_0=500000 +ellps=GRS80 +towgs84=0,0,0,0,0,0,0 +units=m +no_defs +type=crs","bbox":[38.17,-89.57,36.49,-81.95],"unit":"metre","accuracy":2},"9474":{"code":"9474","kind":"CRS-GEOGCRS","name":"PZ-90.02","wkt":"GEOGCRS[\"PZ-90.02\", DYNAMIC[FRAMEEPOCH[2002.0]],DATUM[\"Parametry Zemli 1990.02\",ELLIPSOID[\"PZ-90\",6378136,298.257839303,LENGTHUNIT[\"metre\",1,ID[\"EPSG\",9001]],ID[\"EPSG\",7054]],ID[\"EPSG\",1157]],CS[ellipsoidal,2,ID[\"EPSG\",6422]],AXIS[\"Geodetic latitude (Lat)\",north],AXIS[\"Geodetic longitude (Lon)\",east],ANGLEUNIT[\"degree\",0.0174532925199433,ID[\"EPSG\",9102]],ID[\"EPSG\",9474]]","proj4":"+proj=longlat +a=6378136 +rf=298.257839303 +no_defs +type=crs +axis=neu","bbox":[90,-180,-90,180],"unit":"degree (supplier to define representation)","accuracy":null},"21474":{"accuracy":1,"authority":"EPSG","bbox":[47.23,77.98,29.16,84],"code":"21474","default_trans":15921,"kind":"CRS-PROJCRS","name":"Beijing 1954 / Gauss-Kruger 14N","proj4":"+proj=tmerc +lat_0=0 +lon_0=81 +k=1 +x_0=500000 +y_0=0 +ellps=krass +towgs84=15.8,-154.4,-82.3,0,0,0,0 +units=m +no_defs +type=crs","trans":[15918,15919,15920,15921,15935,15936],"unit":"metre","wkt":"PROJCS[\"Beijing 1954 / Gauss-Kruger 14N\",GEOGCS[\"Beijing 1954\",DATUM[\"Beijing_1954\",SPHEROID[\"Krassowsky 1940\",6378245,298.3],TOWGS84[15.8,-154.4,-82.3,0,0,0,0]],PRIMEM[\"Greenwich\",0,AUTHORITY[\"EPSG\",\"8901\"]],UNIT[\"degree\",0.0174532925199433,AUTHORITY[\"EPSG\",\"9122\"]],AUTHORITY[\"EPSG\",\"4214\"]],PROJECTION[\"Transverse_Mercator\"],PARAMETER[\"latitude_of_origin\",0],PARAMETER[\"central_meridian\",81],PARAMETER[\"scale_factor\",1],PARAMETER[\"false_easting\",500000],PARAMETER[\"false_northing\",0],UNIT[\"metre\",1,AUTHORITY[\"EPSG\",\"9001\"]],AUTHORITY[\"EPSG\",\"21474\"]]"},"28474":{"accuracy":4.5,"authority":"EPSG","bbox":[81.03,78,41.04,84.01],"code":"28474","default_trans":15865,"kind":"CRS-PROJCRS","name":"Pulkovo 1942 / Gauss-Kruger 14N","proj4":"+proj=tmerc +lat_0=0 +lon_0=81 +k=1 +x_0=500000 +y_0=0 +ellps=krass +towgs84=25,-141,-78.5,0,-0.35,-0.736,0 +units=m +no_defs +type=crs","trans":[1254,1267,1274,1287,1288,1289,1290,1291,1292,1293,1303,1310,1332,1334,1679,1807,1808,1809,5044,5586,6899,8199,8236,8658,15844,15865],"unit":"metre","wkt":"PROJCS[\"Pulkovo 1942 / Gauss-Kruger 14N\",GEOGCS[\"Pulkovo 1942\",DATUM[\"Pulkovo_1942\",SPHEROID[\"Krassowsky 1940\",6378245,298.3],TOWGS84[25,-141,-78.5,0,-0.35,-0.736,0]],PRIMEM[\"Greenwich\",0,AUTHORITY[\"EPSG\",\"8901\"]],UNIT[\"degree\",0.0174532925199433,AUTHORITY[\"EPSG\",\"9122\"]],AUTHORITY[\"EPSG\",\"4284\"]],PROJECTION[\"Transverse_Mercator\"],PARAMETER[\"latitude_of_origin\",0],PARAMETER[\"central_meridian\",81],PARAMETER[\"scale_factor\",1],PARAMETER[\"false_easting\",500000],PARAMETER[\"false_northing\",0],UNIT[\"metre\",1,AUTHORITY[\"EPSG\",\"9001\"]],AUTHORITY[\"EPSG\",\"28474\"]]"},"102474":{"code":"102474","kind":"CRS-PROJCRS","name":"Cape Lo23","wkt":"PROJCS[\"Cape_Lo23\",GEOGCS[\"Cape\",DATUM[\"Cape\",SPHEROID[\"Clarke 1880 (Arc)\",6378249.145,293.4663077,AUTHORITY[\"EPSG\",\"7013\"]],AUTHORITY[\"EPSG\",\"6222\"]],PRIMEM[\"Greenwich\",0,AUTHORITY[\"EPSG\",\"8901\"]],UNIT[\"degree\",0.0174532925199433,AUTHORITY[\"EPSG\",\"9122\"]],AUTHORITY[\"EPSG\",\"4222\"]],PROJECTION[\"Transverse_Mercator\"],PARAMETER[\"latitude_of_origin\",0],PARAMETER[\"central_meridian\",23],PARAMETER[\"scale_factor\",-1],PARAMETER[\"false_easting\",0],PARAMETER[\"false_northing\",0],UNIT[\"metre\",1,AUTHORITY[\"EPSG\",\"9001\"]],AXIS[\"Easting\",EAST],AXIS[\"Northing\",NORTH],AUTHORITY[\"ESRI\",\"102474\"]]","proj4":"+proj=tmerc +lat_0=0 +lon_0=23 +k=-1 +x_0=0 +y_0=0 +a=6378249.145 +rf=293.4663077 +units=m +no_defs +type=crs","bbox":[-25.26,22,-34.26,24.01],"unit":null,"accuracy":null},"103474":{"code":"103474","kind":"CRS-PROJCRS","name":"NAD 1983 (CORS96) SPCS Nebraska","wkt":"PROJCS[\"NAD_1983_CORS96_StatePlane_Nebraska_FIPS_2600\",GEOGCS[\"NAD83(CORS96)\",DATUM[\"NAD83_Continuously_Operating_Reference_Station_1996\",SPHEROID[\"GRS 1980\",6378137,298.257222101,AUTHORITY[\"EPSG\",\"7019\"]],AUTHORITY[\"EPSG\",\"1133\"]],PRIMEM[\"Greenwich\",0,AUTHORITY[\"EPSG\",\"8901\"]],UNIT[\"degree\",0.0174532925199433,AUTHORITY[\"EPSG\",\"9122\"]],AUTHORITY[\"EPSG\",\"6783\"]],PROJECTION[\"Lambert_Conformal_Conic_2SP\"],PARAMETER[\"latitude_of_origin\",39.8333333333333],PARAMETER[\"central_meridian\",-100],PARAMETER[\"standard_parallel_1\",40],PARAMETER[\"standard_parallel_2\",43],PARAMETER[\"false_easting\",500000],PARAMETER[\"false_northing\",0],UNIT[\"metre\",1,AUTHORITY[\"EPSG\",\"9001\"]],AXIS[\"Easting\",EAST],AXIS[\"Northing\",NORTH],AUTHORITY[\"ESRI\",\"103474\"]]","proj4":"+proj=lcc +lat_0=39.8333333333333 +lon_0=-100 +lat_1=40 +lat_2=43 +x_0=500000 +y_0=0 +ellps=GRS80 +units=m +no_defs +type=crs","bbox":[43.01,-104.06,39.99,-95.3],"unit":null,"accuracy":null}}