{"2535":{"code":"2535","kind":"CRS-PROJCRS","name":"Pulkovo 1942 / 3-degree Gauss-Kruger zone 19","wkt":"PROJCRS[\"Pulkovo 1942 / 3-degree Gauss-Kruger zone 19\",BASEGEOGCRS[\"Pulkovo 1942\",DATUM[\"Pulkovo 1942\",ELLIPSOID[\"Krassowsky 1940\",6378245,298.3,LENGTHUNIT[\"metre\",1,ID[\"EPSG\",9001]],ID[\"EPSG\",7024]],ID[\"EPSG\",6284]],ID[\"EPSG\",4284]],CONVERSION[\"3-degree Gauss-Kruger zone 19\",METHOD[\"Transverse Mercator\",ID[\"EPSG\",9807]],PARAMETER[\"Latitude of natural origin\",0,ANGLEUNIT[\"degree\",0.0174532925199433,ID[\"EPSG\",9102]],ID[\"EPSG\",8801]],PARAMETER[\"Longitude of natural origin\",57,ANGLEUNIT[\"degree\",0.0174532925199433,ID[\"EPSG\",9102]],ID[\"EPSG\",8802]],PARAMETER[\"Scale factor at natural origin\",1,SCALEUNIT[\"unity\",1,ID[\"EPSG\",9201]],ID[\"EPSG\",8805]],PARAMETER[\"False easting\",19500000,LENGTHUNIT[\"metre\",1,ID[\"EPSG\",9001]],ID[\"EPSG\",8806]],PARAMETER[\"False northing\",0,LENGTHUNIT[\"metre\",1,ID[\"EPSG\",9001]],ID[\"EPSG\",8807]],ID[\"EPSG\",16279]],CS[Cartesian,2,ID[\"EPSG\",4530]],AXIS[\"Northing (X)\",north],AXIS[\"Easting (Y)\",east],LENGTHUNIT[\"metre\",1,ID[\"EPSG\",9001]],ID[\"EPSG\",2535]]","proj4":"+proj=tmerc +lat_0=0 +lon_0=57 +k=1 +x_0=19500000 +y_0=0 +ellps=krass +towgs84=25,-141,-78.5,0,-0.35,-0.736,0 +units=m +no_defs +type=crs +axis=neu","bbox":[81.89,55.5,37.64,58.5],"unit":"metre","accuracy":4.5},"3535":{"code":"3535","kind":"CRS-PROJCRS","name":"NAD83(NSRS2007) / Indiana West (ftUS)","wkt":"PROJCRS[\"NAD83(NSRS2007) / Indiana West (ftUS)\",BASEGEOGCRS[\"NAD83(NSRS2007)\",DATUM[\"NAD83 (National Spatial Reference System 2007)\",ELLIPSOID[\"GRS 1980\",6378137,298.257222101,LENGTHUNIT[\"metre\",1,ID[\"EPSG\",9001]],ID[\"EPSG\",7019]],ID[\"EPSG\",6759]],ID[\"EPSG\",4759]],CONVERSION[\"SPCS83 Indiana West zone (US survey foot)\",METHOD[\"Transverse Mercator\",ID[\"EPSG\",9807]],PARAMETER[\"Latitude of natural origin\",37.5000000000003,ANGLEUNIT[\"degree\",0.0174532925199433,ID[\"EPSG\",9102]],ID[\"EPSG\",8801]],PARAMETER[\"Longitude of natural origin\",-87.0833333333336,ANGLEUNIT[\"degree\",0.0174532925199433,ID[\"EPSG\",9102]],ID[\"EPSG\",8802]],PARAMETER[\"Scale factor at natural origin\",0.999966667,SCALEUNIT[\"unity\",1,ID[\"EPSG\",9201]],ID[\"EPSG\",8805]],PARAMETER[\"False easting\",2952750,LENGTHUNIT[\"US survey foot\",0.304800609601219,ID[\"EPSG\",9003]],ID[\"EPSG\",8806]],PARAMETER[\"False northing\",820208.333,LENGTHUNIT[\"US survey foot\",0.304800609601219,ID[\"EPSG\",9003]],ID[\"EPSG\",8807]],ID[\"EPSG\",15373]],CS[Cartesian,2,ID[\"EPSG\",4497]],AXIS[\"Easting (X)\",east],AXIS[\"Northing (Y)\",north],LENGTHUNIT[\"US survey foot\",0.304800609601219,ID[\"EPSG\",9003]],ID[\"EPSG\",3535]]","proj4":"+proj=tmerc +lat_0=37.5 +lon_0=-87.0833333333333 +k=0.999966667 +x_0=900000 +y_0=249999.9998984 +ellps=GRS80 +towgs84=0,0,0,0,0,0,0 +units=us-ft +no_defs +type=crs","bbox":[41.77,-88.06,37.77,-86.24],"unit":"US survey foot","accuracy":2},"4535":{"code":"4535","kind":"CRS-PROJCRS","name":"CGCS2000 / 3-degree Gauss-Kruger CM 78E","wkt":"PROJCRS[\"CGCS2000 / 3-degree Gauss-Kruger CM 78E\",BASEGEOGCRS[\"China Geodetic Coordinate System 2000\",DATUM[\"China 2000\",ELLIPSOID[\"CGCS2000\",6378137,298.257222101,LENGTHUNIT[\"metre\",1,ID[\"EPSG\",9001]],ID[\"EPSG\",1024]],ID[\"EPSG\",1043]],ID[\"EPSG\",4490]],CONVERSION[\"3-degree Gauss-Kruger CM 78E\",METHOD[\"Transverse Mercator\",ID[\"EPSG\",9807]],PARAMETER[\"Latitude of natural origin\",0,ANGLEUNIT[\"degree\",0.0174532925199433,ID[\"EPSG\",9102]],ID[\"EPSG\",8801]],PARAMETER[\"Longitude of natural origin\",78,ANGLEUNIT[\"degree\",0.0174532925199433,ID[\"EPSG\",9102]],ID[\"EPSG\",8802]],PARAMETER[\"Scale factor at natural origin\",1,SCALEUNIT[\"unity\",1,ID[\"EPSG\",9201]],ID[\"EPSG\",8805]],PARAMETER[\"False easting\",500000,LENGTHUNIT[\"metre\",1,ID[\"EPSG\",9001]],ID[\"EPSG\",8806]],PARAMETER[\"False northing\",0,LENGTHUNIT[\"metre\",1,ID[\"EPSG\",9001]],ID[\"EPSG\",8807]],ID[\"EPSG\",16386]],CS[Cartesian,2,ID[\"EPSG\",4530]],AXIS[\"Northing (X)\",north],AXIS[\"Easting (Y)\",east],LENGTHUNIT[\"metre\",1,ID[\"EPSG\",9001]],ID[\"EPSG\",4535]]","proj4":"+proj=tmerc +lat_0=0 +lon_0=78 +k=1 +x_0=500000 +y_0=0 +ellps=GRS80 +units=m +no_defs +type=crs +axis=neu","bbox":[41.83,76.5,31.03,79.5],"unit":"metre","accuracy":null},"5535":{"code":"5535","kind":"CRS-PROJCRS","name":"SAD69(96) / UTM zone 25S","wkt":"PROJCRS[\"SAD69(96) / UTM zone 25S\",BASEGEOGCRS[\"SAD69(96)\",DATUM[\"South American Datum 1969(96)\",ELLIPSOID[\"GRS 1967 Modified\",6378160,298.25,LENGTHUNIT[\"metre\",1,ID[\"EPSG\",9001]],ID[\"EPSG\",7050]],ID[\"EPSG\",1075]],ID[\"EPSG\",5527]],CONVERSION[\"UTM zone 25S\",METHOD[\"Transverse Mercator\",ID[\"EPSG\",9807]],PARAMETER[\"Latitude of natural origin\",0,ANGLEUNIT[\"degree\",0.0174532925199433,ID[\"EPSG\",9102]],ID[\"EPSG\",8801]],PARAMETER[\"Longitude of natural origin\",-33,ANGLEUNIT[\"degree\",0.0174532925199433,ID[\"EPSG\",9102]],ID[\"EPSG\",8802]],PARAMETER[\"Scale factor at natural origin\",0.9996,SCALEUNIT[\"unity\",1,ID[\"EPSG\",9201]],ID[\"EPSG\",8805]],PARAMETER[\"False easting\",500000,LENGTHUNIT[\"metre\",1,ID[\"EPSG\",9001]],ID[\"EPSG\",8806]],PARAMETER[\"False northing\",10000000,LENGTHUNIT[\"metre\",1,ID[\"EPSG\",9001]],ID[\"EPSG\",8807]],ID[\"EPSG\",16125]],CS[Cartesian,2,ID[\"EPSG\",4400]],AXIS[\"Easting (E)\",east],AXIS[\"Northing (N)\",north],LENGTHUNIT[\"metre\",1,ID[\"EPSG\",9001]],ID[\"EPSG\",5535]]","proj4":"+proj=utm +zone=25 +south +ellps=aust_SA +towgs84=-67.35,3.88,-38.22,0,0,0,0 +units=m +no_defs +type=crs","bbox":[4.19,-36,-23.8,-29.99],"unit":"metre","accuracy":5},"6535":{"code":"6535","kind":"CRS-PROJCRS","name":"NAD83(2011) / New York Central (ftUS)","wkt":"PROJCRS[\"NAD83(2011) / New York Central (ftUS)\",BASEGEOGCRS[\"NAD83(2011)\",DATUM[\"NAD83 (National Spatial Reference System 2011)\",ELLIPSOID[\"GRS 1980\",6378137,298.257222101,LENGTHUNIT[\"metre\",1,ID[\"EPSG\",9001]],ID[\"EPSG\",7019]], ANCHOREPOCH[2010],ID[\"EPSG\",1116]],ID[\"EPSG\",6318]],CONVERSION[\"SPCS83 New York Central zone (US survey foot)\",METHOD[\"Transverse Mercator\",ID[\"EPSG\",9807]],PARAMETER[\"Latitude of natural origin\",40,ANGLEUNIT[\"degree\",0.0174532925199433,ID[\"EPSG\",9102]],ID[\"EPSG\",8801]],PARAMETER[\"Longitude of natural origin\",-76.5833333333336,ANGLEUNIT[\"degree\",0.0174532925199433,ID[\"EPSG\",9102]],ID[\"EPSG\",8802]],PARAMETER[\"Scale factor at natural origin\",0.9999375,SCALEUNIT[\"unity\",1,ID[\"EPSG\",9201]],ID[\"EPSG\",8805]],PARAMETER[\"False easting\",820208.333,LENGTHUNIT[\"US survey foot\",0.304800609601219,ID[\"EPSG\",9003]],ID[\"EPSG\",8806]],PARAMETER[\"False northing\",0,LENGTHUNIT[\"US survey foot\",0.304800609601219,ID[\"EPSG\",9003]],ID[\"EPSG\",8807]],ID[\"EPSG\",15343]],CS[Cartesian,2,ID[\"EPSG\",4497]],AXIS[\"Easting (X)\",east],AXIS[\"Northing (Y)\",north],LENGTHUNIT[\"US survey foot\",0.304800609601219,ID[\"EPSG\",9003]],ID[\"EPSG\",6535]]","proj4":"+proj=tmerc +lat_0=40 +lon_0=-76.5833333333333 +k=0.9999375 +x_0=249999.9998984 +y_0=0 +ellps=GRS80 +towgs84=0,0,0,0,0,0,0 +units=us-ft +no_defs +type=crs","bbox":[44.41,-77.75,41.99,-75.06],"unit":"US survey foot","accuracy":2},"7535":{"code":"7535","kind":"CRS-PROJCRS","name":"NAD83(2011) / WISCRS Calumet, Fond du Lac, Outagamie and Winnebago (m)","wkt":"PROJCRS[\"NAD83(2011) / WISCRS Calumet, Fond du Lac, Outagamie and Winnebago (m)\",BASEGEOGCRS[\"NAD83(2011)\",DATUM[\"NAD83 (National Spatial Reference System 2011)\",ELLIPSOID[\"GRS 1980\",6378137,298.257222101,LENGTHUNIT[\"metre\",1,ID[\"EPSG\",9001]],ID[\"EPSG\",7019]], ANCHOREPOCH[2010],ID[\"EPSG\",1116]],ID[\"EPSG\",6318]],CONVERSION[\"WISCRS Calumet, Fond du Lac, Outagamie and Winnebago Counties (m)\",METHOD[\"Transverse Mercator\",ID[\"EPSG\",9807]],PARAMETER[\"Latitude of natural origin\",42.7194444444447,ANGLEUNIT[\"degree\",0.0174532925199433,ID[\"EPSG\",9102]],ID[\"EPSG\",8801]],PARAMETER[\"Longitude of natural origin\",-88.5000000000003,ANGLEUNIT[\"degree\",0.0174532925199433,ID[\"EPSG\",9102]],ID[\"EPSG\",8802]],PARAMETER[\"Scale factor at natural origin\",1.0000286569,SCALEUNIT[\"unity\",1,ID[\"EPSG\",9201]],ID[\"EPSG\",8805]],PARAMETER[\"False easting\",244754.8893,LENGTHUNIT[\"metre\",1,ID[\"EPSG\",9001]],ID[\"EPSG\",8806]],PARAMETER[\"False northing\",0.0049,LENGTHUNIT[\"metre\",1,ID[\"EPSG\",9001]],ID[\"EPSG\",8807]],ID[\"EPSG\",7486]],CS[Cartesian,2,ID[\"EPSG\",4499]],AXIS[\"Easting (X)\",east],AXIS[\"Northing (Y)\",north],LENGTHUNIT[\"metre\",1,ID[\"EPSG\",9001]],ID[\"EPSG\",7535]]","proj4":"+proj=tmerc +lat_0=42.7194444444444 +lon_0=-88.5 +k=1.0000286569 +x_0=244754.8893 +y_0=0.0049 +ellps=GRS80 +towgs84=0,0,0,0,0,0,0 +units=m +no_defs +type=crs","bbox":[44.6,-88.89,43.54,-88.04],"unit":"metre","accuracy":2},"8535":{"code":"8535","kind":"CRS-PROJCRS","name":"NAD83(2011) / KS RCS zone 16","wkt":"PROJCRS[\"NAD83(2011) / KS RCS zone 16\",BASEGEOGCRS[\"NAD83(2011)\",DATUM[\"NAD83 (National Spatial Reference System 2011)\",ELLIPSOID[\"GRS 1980\",6378137,298.257222101,LENGTHUNIT[\"metre\",1,ID[\"EPSG\",9001]],ID[\"EPSG\",7019]], ANCHOREPOCH[2010],ID[\"EPSG\",1116]],ID[\"EPSG\",6318]],CONVERSION[\"Kansas regional zone 16 Pratt (ftUS)\",METHOD[\"Transverse Mercator\",ID[\"EPSG\",9807]],PARAMETER[\"Latitude of natural origin\",36.7500000000003,ANGLEUNIT[\"degree\",0.0174532925199433,ID[\"EPSG\",9102]],ID[\"EPSG\",8801]],PARAMETER[\"Longitude of natural origin\",-98.5500000000003,ANGLEUNIT[\"degree\",0.0174532925199433,ID[\"EPSG\",9102]],ID[\"EPSG\",8802]],PARAMETER[\"Scale factor at natural origin\",1.000069,SCALEUNIT[\"unity\",1,ID[\"EPSG\",9201]],ID[\"EPSG\",8805]],PARAMETER[\"False easting\",16500000,LENGTHUNIT[\"US survey foot\",0.304800609601219,ID[\"EPSG\",9003]],ID[\"EPSG\",8806]],PARAMETER[\"False northing\",0,LENGTHUNIT[\"US survey foot\",0.304800609601219,ID[\"EPSG\",9003]],ID[\"EPSG\",8807]],ID[\"EPSG\",8505]],CS[Cartesian,2,ID[\"EPSG\",4497]],AXIS[\"Easting (X)\",east],AXIS[\"Northing (Y)\",north],LENGTHUNIT[\"US survey foot\",0.304800609601219,ID[\"EPSG\",9003]],ID[\"EPSG\",8535]]","proj4":"+proj=tmerc +lat_0=36.75 +lon_0=-98.55 +k=1.000069 +x_0=5029210.05842011 +y_0=0 +ellps=GRS80 +towgs84=0,0,0,0,0,0,0 +units=us-ft +no_defs +type=crs","bbox":[38.27,-99.03,36.99,-98.34],"unit":"US survey foot","accuracy":2},"9535":{"code":"9535","kind":"CRS-COMPOUNDCRS","name":"RGAF09 + IGN 1988 SM height","wkt":"COMPOUNDCRS[\"RGAF09 + IGN 1988 SM height\",GEOGCRS[\"RGAF09\",DATUM[\"Reseau Geodesique des Antilles Francaises 2009\",ELLIPSOID[\"GRS 1980\",6378137,298.257222101,LENGTHUNIT[\"metre\",1,ID[\"EPSG\",9001]],ID[\"EPSG\",7019]],ID[\"EPSG\",1073]],CS[ellipsoidal,2,ID[\"EPSG\",6422]],AXIS[\"Geodetic latitude (Lat)\",north],AXIS[\"Geodetic longitude (Lon)\",east],ANGLEUNIT[\"degree\",0.0174532925199433,ID[\"EPSG\",9102]],ID[\"EPSG\",5489]],VERTCRS[\"IGN 1988 SM height\",VDATUM[\"IGN 1988 SM\",ID[\"EPSG\",5214]],CS[vertical,1,ID[\"EPSG\",6499]],AXIS[\"Gravity-related height (H)\",up],LENGTHUNIT[\"metre\",1,ID[\"EPSG\",9001]],GEOIDMODEL[\"RRAF 1991 to IGN 1988 SM height (1)\",ID[\"EPSG\",4564]],GEOIDMODEL[\"RGAF09 to IGN 1988 SM height (1)\",ID[\"EPSG\",5505]],GEOIDMODEL[\"RGAF09 to IGN 1988 SM height (2)\",ID[\"EPSG\",9188]],ID[\"EPSG\",5620]],ID[\"EPSG\",9535]]","proj4":"+proj=longlat +ellps=GRS80 +vunits=m +no_defs +type=crs +axis=neu","bbox":[18.17,-63.21,18.01,-62.96],"unit":null,"accuracy":null},"32535":{"code":"32535","kind":"CRS-PROJCRS","name":"WGS 72BE / UTM zone 35S","wkt":"PROJCRS[\"WGS 72BE / UTM zone 35S\",BASEGEOGCRS[\"WGS 72BE\", DYNAMIC[FRAMEEPOCH[1972.0]],DATUM[\"WGS 72 Transit Broadcast Ephemeris\",ELLIPSOID[\"WGS 72\",6378135,298.26,LENGTHUNIT[\"metre\",1,ID[\"EPSG\",9001]],ID[\"EPSG\",7043]],ID[\"EPSG\",6324]],ID[\"EPSG\",4324]],CONVERSION[\"UTM zone 35S\",METHOD[\"Transverse Mercator\",ID[\"EPSG\",9807]],PARAMETER[\"Latitude of natural origin\",0,ANGLEUNIT[\"degree\",0.0174532925199433,ID[\"EPSG\",9102]],ID[\"EPSG\",8801]],PARAMETER[\"Longitude of natural origin\",27,ANGLEUNIT[\"degree\",0.0174532925199433,ID[\"EPSG\",9102]],ID[\"EPSG\",8802]],PARAMETER[\"Scale factor at natural origin\",0.9996,SCALEUNIT[\"unity\",1,ID[\"EPSG\",9201]],ID[\"EPSG\",8805]],PARAMETER[\"False easting\",500000,LENGTHUNIT[\"metre\",1,ID[\"EPSG\",9001]],ID[\"EPSG\",8806]],PARAMETER[\"False northing\",10000000,LENGTHUNIT[\"metre\",1,ID[\"EPSG\",9001]],ID[\"EPSG\",8807]],ID[\"EPSG\",16135]],CS[Cartesian,2,ID[\"EPSG\",4400]],AXIS[\"Easting (E)\",east],AXIS[\"Northing (N)\",north],LENGTHUNIT[\"metre\",1,ID[\"EPSG\",9001]],ID[\"EPSG\",32535]]","proj4":"+proj=utm +zone=35 +south +ellps=WGS72 +towgs84=0,0,1.9,0,0,0.814,-0.38 +units=m +no_defs +type=crs","bbox":[0,24,-80,30],"unit":"metre","accuracy":2},"102535":{"accuracy":"","authority":"ESRI","bbox":[46.08,-122.05,45.49,-118.89],"code":"102535","default_trans":0,"kind":"CRS-PROJCRS","name":"OCRS Columbia River East NAD 1983 CORS96 LCC (M)","proj4":"+proj=lcc +lat_1=45.6666666666667 +lat_0=45.6666666666667 +lon_0=-120.5 +k_0=1.000008 +x_0=150000 +y_0=30000 +ellps=GRS80 +units=m +no_defs +type=crs","trans":[],"unit":"","wkt":"PROJCS[\"OCRS_Columbia_River_East_NAD_1983_CORS96_LCC_Meters (deprecated)\",GEOGCS[\"NAD83(CORS96)\",DATUM[\"NAD83_Continuously_Operating_Reference_Station_1996\",SPHEROID[\"GRS 1980\",6378137,298.257222101,AUTHORITY[\"EPSG\",\"7019\"]],AUTHORITY[\"EPSG\",\"1133\"]],PRIMEM[\"Greenwich\",0,AUTHORITY[\"EPSG\",\"8901\"]],UNIT[\"degree\",0.0174532925199433,AUTHORITY[\"EPSG\",\"9122\"]],AUTHORITY[\"EPSG\",\"6783\"]],PROJECTION[\"Lambert_Conformal_Conic_1SP\"],PARAMETER[\"latitude_of_origin\",45.6666666666667],PARAMETER[\"central_meridian\",-120.5],PARAMETER[\"scale_factor\",1.000008],PARAMETER[\"false_easting\",150000],PARAMETER[\"false_northing\",30000],UNIT[\"metre\",1,AUTHORITY[\"EPSG\",\"9001\"]],AXIS[\"Easting\",EAST],AXIS[\"Northing\",NORTH],AUTHORITY[\"ESRI\",\"102535\"]]"},"103535":{"accuracy":"","authority":"ESRI","bbox":[84.01,24,41.24,30.01],"code":"103535","default_trans":0,"kind":"CRS-PROJCRS","name":"ETRF 1989 UTM Zone 35N (DEPRECATED)","proj4":"+proj=utm +zone=35 +ellps=GRS80 +units=m +no_defs +type=crs","trans":[],"unit":"","wkt":"PROJCS[\"ETRF_1989_UTM_Zone_35N (deprecated)\",GEOGCS[\"ETRF89\",DATUM[\"European_Terrestrial_Reference_Frame_1989\",SPHEROID[\"GRS 1980\",6378137,298.257222101,AUTHORITY[\"EPSG\",\"7019\"]],AUTHORITY[\"EPSG\",\"1178\"]],PRIMEM[\"Greenwich\",0,AUTHORITY[\"EPSG\",\"8901\"]],UNIT[\"degree\",0.0174532925199433,AUTHORITY[\"EPSG\",\"9122\"]],AUTHORITY[\"EPSG\",\"9059\"]],PROJECTION[\"Transverse_Mercator\"],PARAMETER[\"latitude_of_origin\",0],PARAMETER[\"central_meridian\",27],PARAMETER[\"scale_factor\",0.9996],PARAMETER[\"false_easting\",500000],PARAMETER[\"false_northing\",0],UNIT[\"metre\",1,AUTHORITY[\"EPSG\",\"9001\"]],AXIS[\"Easting\",EAST],AXIS[\"Northing\",NORTH],AUTHORITY[\"ESRI\",\"103535\"]]"}}