{"2667":{"code":"2667","kind":"CRS-PROJCRS","name":"Pulkovo 1995 / 3-degree Gauss-Kruger zone 33","wkt":"PROJCRS[\"Pulkovo 1995 / 3-degree Gauss-Kruger zone 33\",BASEGEOGCRS[\"Pulkovo 1995\",DATUM[\"Pulkovo 1995\",ELLIPSOID[\"Krassowsky 1940\",6378245,298.3,LENGTHUNIT[\"metre\",1,ID[\"EPSG\",9001]],ID[\"EPSG\",7024]],ID[\"EPSG\",6200]],ID[\"EPSG\",4200]],CONVERSION[\"3-degree Gauss-Kruger zone 33\",METHOD[\"Transverse Mercator\",ID[\"EPSG\",9807]],PARAMETER[\"Latitude of natural origin\",0,ANGLEUNIT[\"degree\",0.0174532925199433,ID[\"EPSG\",9102]],ID[\"EPSG\",8801]],PARAMETER[\"Longitude of natural origin\",99,ANGLEUNIT[\"degree\",0.0174532925199433,ID[\"EPSG\",9102]],ID[\"EPSG\",8802]],PARAMETER[\"Scale factor at natural origin\",1,SCALEUNIT[\"unity\",1,ID[\"EPSG\",9201]],ID[\"EPSG\",8805]],PARAMETER[\"False easting\",33500000,LENGTHUNIT[\"metre\",1,ID[\"EPSG\",9001]],ID[\"EPSG\",8806]],PARAMETER[\"False northing\",0,LENGTHUNIT[\"metre\",1,ID[\"EPSG\",9001]],ID[\"EPSG\",8807]],ID[\"EPSG\",16293]],CS[Cartesian,2,ID[\"EPSG\",4530]],AXIS[\"Northing (X)\",north],AXIS[\"Easting (Y)\",east],LENGTHUNIT[\"metre\",1,ID[\"EPSG\",9001]],ID[\"EPSG\",2667]]","proj4":"+proj=tmerc +lat_0=0 +lon_0=99 +k=1 +x_0=33500000 +y_0=0 +ellps=krass +towgs84=24.47,-130.89,-81.56,0,0,-0.13,-0.22 +units=m +no_defs +type=crs +axis=neu","bbox":[80.9,97.5,49.79,100.5],"unit":"metre","accuracy":1},"3667":{"code":"3667","kind":"CRS-PROJCRS","name":"NAD83(NSRS2007) / Texas North","wkt":"PROJCRS[\"NAD83(NSRS2007) / Texas North\",BASEGEOGCRS[\"NAD83(NSRS2007)\",DATUM[\"NAD83 (National Spatial Reference System 2007)\",ELLIPSOID[\"GRS 1980\",6378137,298.257222101,LENGTHUNIT[\"metre\",1,ID[\"EPSG\",9001]],ID[\"EPSG\",7019]],ID[\"EPSG\",6759]],ID[\"EPSG\",4759]],CONVERSION[\"SPCS83 Texas North zone (meter)\",METHOD[\"Lambert Conic Conformal (2SP)\",ID[\"EPSG\",9802]],PARAMETER[\"Latitude of false origin\",34,ANGLEUNIT[\"degree\",0.0174532925199433,ID[\"EPSG\",9102]],ID[\"EPSG\",8821]],PARAMETER[\"Longitude of false origin\",-101.5,ANGLEUNIT[\"degree\",0.0174532925199433,ID[\"EPSG\",9102]],ID[\"EPSG\",8822]],PARAMETER[\"Latitude of 1st standard parallel\",36.1833333333336,ANGLEUNIT[\"degree\",0.0174532925199433,ID[\"EPSG\",9102]],ID[\"EPSG\",8823]],PARAMETER[\"Latitude of 2nd standard parallel\",34.6500000000003,ANGLEUNIT[\"degree\",0.0174532925199433,ID[\"EPSG\",9102]],ID[\"EPSG\",8824]],PARAMETER[\"Easting at false origin\",200000,LENGTHUNIT[\"metre\",1,ID[\"EPSG\",9001]],ID[\"EPSG\",8826]],PARAMETER[\"Northing at false origin\",1000000,LENGTHUNIT[\"metre\",1,ID[\"EPSG\",9001]],ID[\"EPSG\",8827]],ID[\"EPSG\",14231]],CS[Cartesian,2,ID[\"EPSG\",4499]],AXIS[\"Easting (X)\",east],AXIS[\"Northing (Y)\",north],LENGTHUNIT[\"metre\",1,ID[\"EPSG\",9001]],ID[\"EPSG\",3667]]","proj4":"+proj=lcc +lat_0=34 +lon_0=-101.5 +lat_1=36.1833333333333 +lat_2=34.65 +x_0=200000 +y_0=1000000 +ellps=GRS80 +towgs84=0,0,0,0,0,0,0 +units=m +no_defs +type=crs","bbox":[36.5,-103.03,34.3,-99.99],"unit":"metre","accuracy":2},"4667":{"code":"4667","kind":"CRS-GEOGCRS","name":"IKBD-92","wkt":"GEOGCRS[\"IKBD-92\",DATUM[\"Iraq-Kuwait Boundary Datum 1992\",ELLIPSOID[\"WGS 84\",6378137,298.257223563,LENGTHUNIT[\"metre\",1,ID[\"EPSG\",9001]],ID[\"EPSG\",7030]],ID[\"EPSG\",6667]],CS[ellipsoidal,2,ID[\"EPSG\",6422]],AXIS[\"Geodetic latitude (Lat)\",north],AXIS[\"Geodetic longitude (Lon)\",east],ANGLEUNIT[\"degree\",0.0174532925199433,ID[\"EPSG\",9102]],ID[\"EPSG\",4667]]","proj4":"+proj=longlat +ellps=WGS84 +towgs84=0,0,0,0,0,0,0 +no_defs +type=crs +axis=neu","bbox":[30.32,46.36,29.06,48.61],"unit":"degree (supplier to define representation)","accuracy":1},"5667":{"code":"5667","kind":"CRS-PROJCRS","name":"PD/83 / 3-degree Gauss-Kruger zone 4 (E-N)","wkt":"PROJCRS[\"PD/83 / 3-degree Gauss-Kruger zone 4 (E-N)\",BASEGEOGCRS[\"PD/83\",DATUM[\"Potsdam Datum/83\",ELLIPSOID[\"Bessel 1841\",6377397.155,299.1528128,LENGTHUNIT[\"metre\",1,ID[\"EPSG\",9001]],ID[\"EPSG\",7004]],ID[\"EPSG\",6746]],ID[\"EPSG\",4746]],CONVERSION[\"3-degree Gauss-Kruger zone 4\",METHOD[\"Transverse Mercator\",ID[\"EPSG\",9807]],PARAMETER[\"Latitude of natural origin\",0,ANGLEUNIT[\"degree\",0.0174532925199433,ID[\"EPSG\",9102]],ID[\"EPSG\",8801]],PARAMETER[\"Longitude of natural origin\",12,ANGLEUNIT[\"degree\",0.0174532925199433,ID[\"EPSG\",9102]],ID[\"EPSG\",8802]],PARAMETER[\"Scale factor at natural origin\",1,SCALEUNIT[\"unity\",1,ID[\"EPSG\",9201]],ID[\"EPSG\",8805]],PARAMETER[\"False easting\",4500000,LENGTHUNIT[\"metre\",1,ID[\"EPSG\",9001]],ID[\"EPSG\",8806]],PARAMETER[\"False northing\",0,LENGTHUNIT[\"metre\",1,ID[\"EPSG\",9001]],ID[\"EPSG\",8807]],ID[\"EPSG\",16264]],CS[Cartesian,2,ID[\"EPSG\",4400]],AXIS[\"Easting (E)\",east],AXIS[\"Northing (N)\",north],LENGTHUNIT[\"metre\",1,ID[\"EPSG\",9001]],ID[\"EPSG\",5667]]","proj4":"+proj=tmerc +lat_0=0 +lon_0=12 +k=1 +x_0=4500000 +y_0=0 +ellps=bessel +nadgrids=BETA2007.gsb +units=m +no_defs +type=crs","bbox":[51.64,10.5,50.2,12.56],"unit":"metre","accuracy":1},"6667":{"code":"6667","kind":"CRS-GEOG3DCRS","name":"JGD2011","wkt":"GEOGCRS[\"JGD2011\",DATUM[\"Japanese Geodetic Datum 2011\",ELLIPSOID[\"GRS 1980\",6378137,298.257222101,LENGTHUNIT[\"metre\",1,ID[\"EPSG\",9001]],ID[\"EPSG\",7019]],ID[\"EPSG\",1128]],CS[ellipsoidal,3,ID[\"EPSG\",6423]],AXIS[\"Geodetic latitude (Lat)\",north,ANGLEUNIT[\"degree\",0.0174532925199433,ID[\"EPSG\",9102]]],AXIS[\"Geodetic longitude (Lon)\",east,ANGLEUNIT[\"degree\",0.0174532925199433,ID[\"EPSG\",9102]]],AXIS[\"Ellipsoidal height (h)\",up,LENGTHUNIT[\"metre\",1,ID[\"EPSG\",9001]]],ID[\"EPSG\",6667]]","proj4":"+proj=longlat +ellps=GRS80 +no_defs +type=crs","bbox":[46.05,122.38,17.09,157.65],"unit":"degree (supplier to define representation)","accuracy":null},"32667":{"code":"32667","kind":"CRS-PROJCRS","name":"WGS 84 / BLM 17N (ftUS)","wkt":"PROJCRS[\"WGS 84 / BLM 17N (ftUS)\",BASEGEOGCRS[\"WGS 84\",ENSEMBLE[\"World Geodetic System 1984 ensemble\", MEMBER[\"World Geodetic System 1984 (Transit)\", ID[\"EPSG\",1166]], MEMBER[\"World Geodetic System 1984 (G730)\", ID[\"EPSG\",1152]], MEMBER[\"World Geodetic System 1984 (G873)\", ID[\"EPSG\",1153]], MEMBER[\"World Geodetic System 1984 (G1150)\", ID[\"EPSG\",1154]], MEMBER[\"World Geodetic System 1984 (G1674)\", ID[\"EPSG\",1155]], MEMBER[\"World Geodetic System 1984 (G1762)\", ID[\"EPSG\",1156]], MEMBER[\"World Geodetic System 1984 (G2139)\", ID[\"EPSG\",1309]], MEMBER[\"World Geodetic System 1984 (G2296)\", ID[\"EPSG\",1383]], ELLIPSOID[\"WGS 84\",6378137,298.257223563,LENGTHUNIT[\"metre\",1,ID[\"EPSG\",9001]],ID[\"EPSG\",7030]], ENSEMBLEACCURACY[2],ID[\"EPSG\",6326]],ID[\"EPSG\",4326]],CONVERSION[\"BLM zone 17N (US survey foot)\",METHOD[\"Transverse Mercator\",ID[\"EPSG\",9807]],PARAMETER[\"Latitude of natural origin\",0,ANGLEUNIT[\"degree\",0.0174532925199433,ID[\"EPSG\",9102]],ID[\"EPSG\",8801]],PARAMETER[\"Longitude of natural origin\",-81,ANGLEUNIT[\"degree\",0.0174532925199433,ID[\"EPSG\",9102]],ID[\"EPSG\",8802]],PARAMETER[\"Scale factor at natural origin\",0.9996,SCALEUNIT[\"unity\",1,ID[\"EPSG\",9201]],ID[\"EPSG\",8805]],PARAMETER[\"False easting\",1640416.67,LENGTHUNIT[\"US survey foot\",0.304800609601219,ID[\"EPSG\",9003]],ID[\"EPSG\",8806]],PARAMETER[\"False northing\",0,LENGTHUNIT[\"US survey foot\",0.304800609601219,ID[\"EPSG\",9003]],ID[\"EPSG\",8807]],ID[\"EPSG\",15917]],CS[Cartesian,2,ID[\"EPSG\",4497]],AXIS[\"Easting (X)\",east],AXIS[\"Northing (Y)\",north],LENGTHUNIT[\"US survey foot\",0.304800609601219,ID[\"EPSG\",9003]],ID[\"EPSG\",32667]]","proj4":"+proj=tmerc +lat_0=0 +lon_0=-81 +k=0.9996 +x_0=500000.001016002 +y_0=0 +datum=WGS84 +units=us-ft +no_defs +type=crs","bbox":[29.94,-84.09,23.82,-81.17],"unit":"US survey foot","accuracy":null},"102667":{"accuracy":"","authority":"ESRI","bbox":[35.01,-85.61,30.62,-82.99],"code":"102667","default_trans":0,"kind":"CRS-PROJCRS","name":"NAD 1983 SPCS Georgia West (Feet)","proj4":"+proj=tmerc +lat_0=30 +lon_0=-84.1666666666667 +k=0.9999 +x_0=700000 +y_0=0 +datum=NAD83 +units=us-ft +no_defs +type=crs","trans":[],"unit":"","wkt":"PROJCS[\"NAD_1983_StatePlane_Georgia_West_FIPS_1002_Feet (deprecated)\",GEOGCS[\"NAD83\",DATUM[\"North_American_Datum_1983\",SPHEROID[\"GRS 1980\",6378137,298.257222101,AUTHORITY[\"EPSG\",\"7019\"]],AUTHORITY[\"EPSG\",\"6269\"]],PRIMEM[\"Greenwich\",0,AUTHORITY[\"EPSG\",\"8901\"]],UNIT[\"degree\",0.0174532925199433,AUTHORITY[\"EPSG\",\"9122\"]],AUTHORITY[\"EPSG\",\"4269\"]],PROJECTION[\"Transverse_Mercator\"],PARAMETER[\"latitude_of_origin\",30],PARAMETER[\"central_meridian\",-84.1666666666667],PARAMETER[\"scale_factor\",0.9999],PARAMETER[\"false_easting\",2296583.33333333],PARAMETER[\"false_northing\",0],UNIT[\"US survey foot\",0.304800609601219,AUTHORITY[\"EPSG\",\"9003\"]],AXIS[\"Easting\",EAST],AXIS[\"Northing\",NORTH],AUTHORITY[\"ESRI\",\"102667\"]]"},"103667":{"code":"103667","kind":"CRS-PROJCRS","name":"NAD 1983 HARN Adj. Minnesota Pope (meter)","wkt":"PROJCS[\"NAD_1983_HARN_Adj_MN_Pope_Meters\",GEOGCS[\"GCS_NAD_1983_HARN_Adj_MN_Pope\",DATUM[\"D_NAD_1983_HARN_Adj_MN_Pope\",SPHEROID[\"S_GRS_1980_Adj_MN_Pope\",6378502.761,298.257222100883,AUTHORITY[\"ESRI\",\"107759\"]],AUTHORITY[\"ESRI\",\"106759\"]],PRIMEM[\"Greenwich\",0,AUTHORITY[\"EPSG\",\"8901\"]],UNIT[\"degree\",0.0174532925199433,AUTHORITY[\"EPSG\",\"9122\"]],AUTHORITY[\"ESRI\",\"104759\"]],PROJECTION[\"Lambert_Conformal_Conic_2SP\"],PARAMETER[\"latitude_of_origin\",45.2827777777778],PARAMETER[\"central_meridian\",-95.15],PARAMETER[\"standard_parallel_1\",45.35],PARAMETER[\"standard_parallel_2\",45.7],PARAMETER[\"false_easting\",152400.30480061],PARAMETER[\"false_northing\",30480.0609601219],UNIT[\"metre\",1,AUTHORITY[\"EPSG\",\"9001\"]],AXIS[\"Easting\",EAST],AXIS[\"Northing\",NORTH],AUTHORITY[\"ESRI\",\"103667\"]]","proj4":"+proj=lcc +lat_0=45.2827777777778 +lon_0=-95.15 +lat_1=45.35 +lat_2=45.7 +x_0=152400.30480061 +y_0=30480.0609601219 +a=6378502.761 +rf=298.257222100883 +units=m +no_defs +type=crs","bbox":[49.38,-97.22,43.49,-89.49],"unit":null,"accuracy":null}}