{"2719":{"code":"2719","kind":"CRS-PROJCRS","name":"Pulkovo 1995 / 3-degree Gauss-Kruger CM 81E","wkt":"PROJCRS[\"Pulkovo 1995 / 3-degree Gauss-Kruger CM 81E\",BASEGEOGCRS[\"Pulkovo 1995\",DATUM[\"Pulkovo 1995\",ELLIPSOID[\"Krassowsky 1940\",6378245,298.3,LENGTHUNIT[\"metre\",1,ID[\"EPSG\",9001]],ID[\"EPSG\",7024]],ID[\"EPSG\",6200]],ID[\"EPSG\",4200]],CONVERSION[\"Gauss-Kruger CM 81E\",METHOD[\"Transverse Mercator\",ID[\"EPSG\",9807]],PARAMETER[\"Latitude of natural origin\",0,ANGLEUNIT[\"degree\",0.0174532925199433,ID[\"EPSG\",9102]],ID[\"EPSG\",8801]],PARAMETER[\"Longitude of natural origin\",81,ANGLEUNIT[\"degree\",0.0174532925199433,ID[\"EPSG\",9102]],ID[\"EPSG\",8802]],PARAMETER[\"Scale factor at natural origin\",1,SCALEUNIT[\"unity\",1,ID[\"EPSG\",9201]],ID[\"EPSG\",8805]],PARAMETER[\"False easting\",500000,LENGTHUNIT[\"metre\",1,ID[\"EPSG\",9001]],ID[\"EPSG\",8806]],PARAMETER[\"False northing\",0,LENGTHUNIT[\"metre\",1,ID[\"EPSG\",9001]],ID[\"EPSG\",8807]],ID[\"EPSG\",16314]],CS[Cartesian,2,ID[\"EPSG\",4530]],AXIS[\"Northing (X)\",north],AXIS[\"Easting (Y)\",east],LENGTHUNIT[\"metre\",1,ID[\"EPSG\",9001]],ID[\"EPSG\",2719]]","proj4":"+proj=tmerc +lat_0=0 +lon_0=81 +k=1 +x_0=500000 +y_0=0 +ellps=krass +towgs84=24.47,-130.89,-81.56,0,0,-0.13,-0.22 +units=m +no_defs +type=crs +axis=neu","bbox":[81.03,79.5,50.7,82.5],"unit":"metre","accuracy":1},"3719":{"code":"3719","kind":"CRS-PROJCRS","name":"NAD83(NSRS2007) / UTM zone 12N","wkt":"PROJCRS[\"NAD83(NSRS2007) / UTM zone 12N\",BASEGEOGCRS[\"NAD83(NSRS2007)\",DATUM[\"NAD83 (National Spatial Reference System 2007)\",ELLIPSOID[\"GRS 1980\",6378137,298.257222101,LENGTHUNIT[\"metre\",1,ID[\"EPSG\",9001]],ID[\"EPSG\",7019]],ID[\"EPSG\",6759]],ID[\"EPSG\",4759]],CONVERSION[\"UTM zone 12N\",METHOD[\"Transverse Mercator\",ID[\"EPSG\",9807]],PARAMETER[\"Latitude of natural origin\",0,ANGLEUNIT[\"degree\",0.0174532925199433,ID[\"EPSG\",9102]],ID[\"EPSG\",8801]],PARAMETER[\"Longitude of natural origin\",-111,ANGLEUNIT[\"degree\",0.0174532925199433,ID[\"EPSG\",9102]],ID[\"EPSG\",8802]],PARAMETER[\"Scale factor at natural origin\",0.9996,SCALEUNIT[\"unity\",1,ID[\"EPSG\",9201]],ID[\"EPSG\",8805]],PARAMETER[\"False easting\",500000,LENGTHUNIT[\"metre\",1,ID[\"EPSG\",9001]],ID[\"EPSG\",8806]],PARAMETER[\"False northing\",0,LENGTHUNIT[\"metre\",1,ID[\"EPSG\",9001]],ID[\"EPSG\",8807]],ID[\"EPSG\",16012]],CS[Cartesian,2,ID[\"EPSG\",4400]],AXIS[\"Easting (E)\",east],AXIS[\"Northing (N)\",north],LENGTHUNIT[\"metre\",1,ID[\"EPSG\",9001]],ID[\"EPSG\",3719]]","proj4":"+proj=utm +zone=12 +ellps=GRS80 +towgs84=0,0,0,0,0,0,0 +units=m +no_defs +type=crs","bbox":[49.01,-114,31.33,-108],"unit":"metre","accuracy":2},"4719":{"code":"4719","kind":"CRS-GEOGCRS","name":"Easter Island 1967","wkt":"GEOGCRS[\"Easter Island 1967\",DATUM[\"Easter Island 1967\",ELLIPSOID[\"International 1924\",6378388,297,LENGTHUNIT[\"metre\",1,ID[\"EPSG\",9001]],ID[\"EPSG\",7022]],ID[\"EPSG\",6719]],CS[ellipsoidal,2,ID[\"EPSG\",6422]],AXIS[\"Geodetic latitude (Lat)\",north],AXIS[\"Geodetic longitude (Lon)\",east],ANGLEUNIT[\"degree\",0.0174532925199433,ID[\"EPSG\",9102]],ID[\"EPSG\",4719]]","proj4":"+proj=longlat +ellps=intl +towgs84=211,147,111,0,0,0,0 +no_defs +type=crs +axis=neu","bbox":[-27.01,-109.51,-27.25,-109.16],"unit":"degree (supplier to define representation)","accuracy":44},"5719":{"code":"5719","kind":"CRS-VERTCRS","name":"NGF Lallemand height","wkt":"VERTCRS[\"NGF Lallemand height\",VDATUM[\"Nivellement General de la France - Lallemand\",ID[\"EPSG\",5118]],CS[vertical,1,ID[\"EPSG\",6499]],AXIS[\"Gravity-related height (H)\",up],LENGTHUNIT[\"metre\",1,ID[\"EPSG\",9001]],ID[\"EPSG\",5719]]","proj4":"+vunits=m +no_defs +type=crs","bbox":[51.14,-4.87,42.33,8.23],"unit":"metre","accuracy":null},"8719":{"code":"8719","kind":"CRS-COMPOUNDCRS","name":"NAD83 / California zone 6 (ftUS) + NAVD88 height (ftUS)","wkt":"COMPOUNDCRS[\"NAD83 / California zone 6 (ftUS) + NAVD88 height (ftUS)\",PROJCRS[\"NAD83 / California zone 6 (ftUS)\",BASEGEOGCRS[\"NAD83\",DATUM[\"North American Datum 1983\",ELLIPSOID[\"GRS 1980\",6378137,298.257222101,LENGTHUNIT[\"metre\",1,ID[\"EPSG\",9001]],ID[\"EPSG\",7019]],ID[\"EPSG\",6269]],ID[\"EPSG\",4269]],CONVERSION[\"SPCS83 California zone 6 (US survey foot)\",METHOD[\"Lambert Conic Conformal (2SP)\",ID[\"EPSG\",9802]],PARAMETER[\"Latitude of false origin\",32.1666666666669,ANGLEUNIT[\"degree\",0.0174532925199433,ID[\"EPSG\",9102]],ID[\"EPSG\",8821]],PARAMETER[\"Longitude of false origin\",-116.25,ANGLEUNIT[\"degree\",0.0174532925199433,ID[\"EPSG\",9102]],ID[\"EPSG\",8822]],PARAMETER[\"Latitude of 1st standard parallel\",33.8833333333336,ANGLEUNIT[\"degree\",0.0174532925199433,ID[\"EPSG\",9102]],ID[\"EPSG\",8823]],PARAMETER[\"Latitude of 2nd standard parallel\",32.7833333333336,ANGLEUNIT[\"degree\",0.0174532925199433,ID[\"EPSG\",9102]],ID[\"EPSG\",8824]],PARAMETER[\"Easting at false origin\",6561666.667,LENGTHUNIT[\"US survey foot\",0.304800609601219,ID[\"EPSG\",9003]],ID[\"EPSG\",8826]],PARAMETER[\"Northing at false origin\",1640416.667,LENGTHUNIT[\"US survey foot\",0.304800609601219,ID[\"EPSG\",9003]],ID[\"EPSG\",8827]],ID[\"EPSG\",15312]],CS[Cartesian,2,ID[\"EPSG\",4497]],AXIS[\"Easting (X)\",east],AXIS[\"Northing (Y)\",north],LENGTHUNIT[\"US survey foot\",0.304800609601219,ID[\"EPSG\",9003]],ID[\"EPSG\",2230]],VERTCRS[\"NAVD88 height (ftUS)\",BASEVERTCRS[\"NAVD88 height\",VDATUM[\"North American Vertical Datum 1988\",ID[\"EPSG\",5103]],ID[\"EPSG\",5703]],DERIVINGCONVERSION[\"Vertical Axis Unit Conversion\",METHOD[\"Change of Vertical Unit\",ID[\"EPSG\",1104]],ID[\"EPSG\",7813]],CS[vertical,1,ID[\"EPSG\",6497]],AXIS[\"Gravity-related height (H)\",up],LENGTHUNIT[\"US survey foot\",0.304800609601219,ID[\"EPSG\",9003]],ID[\"EPSG\",6360]],ID[\"EPSG\",8719]]","proj4":"+proj=lcc +lat_0=32.1666666666667 +lon_0=-116.25 +lat_1=33.8833333333333 +lat_2=32.7833333333333 +x_0=2000000.0001016 +y_0=500000.0001016 +datum=NAD83 +units=us-ft +vunits=us-ft +no_defs +type=crs","bbox":[34.08,-118.15,32.53,-114.42],"unit":null,"accuracy":null},"22719":{"code":"22719","kind":"CRS-PROJCRS","name":"NAD83(CSRS)v7 / UTM zone 19N","wkt":"PROJCRS[\"NAD83(CSRS)v7 / UTM zone 19N\",BASEGEOGCRS[\"NAD83(CSRS)v7\",DATUM[\"North American Datum of 1983 (CSRS) version 7\",ELLIPSOID[\"GRS 1980\",6378137,298.257222101,LENGTHUNIT[\"metre\",1,ID[\"EPSG\",9001]],ID[\"EPSG\",7019]], ANCHOREPOCH[2010],ID[\"EPSG\",1198]],ID[\"EPSG\",8255]],CONVERSION[\"UTM zone 19N\",METHOD[\"Transverse Mercator\",ID[\"EPSG\",9807]],PARAMETER[\"Latitude of natural origin\",0,ANGLEUNIT[\"degree\",0.0174532925199433,ID[\"EPSG\",9102]],ID[\"EPSG\",8801]],PARAMETER[\"Longitude of natural origin\",-69,ANGLEUNIT[\"degree\",0.0174532925199433,ID[\"EPSG\",9102]],ID[\"EPSG\",8802]],PARAMETER[\"Scale factor at natural origin\",0.9996,SCALEUNIT[\"unity\",1,ID[\"EPSG\",9201]],ID[\"EPSG\",8805]],PARAMETER[\"False easting\",500000,LENGTHUNIT[\"metre\",1,ID[\"EPSG\",9001]],ID[\"EPSG\",8806]],PARAMETER[\"False northing\",0,LENGTHUNIT[\"metre\",1,ID[\"EPSG\",9001]],ID[\"EPSG\",8807]],ID[\"EPSG\",16019]],CS[Cartesian,2,ID[\"EPSG\",4400]],AXIS[\"Easting (E)\",east],AXIS[\"Northing (N)\",north],LENGTHUNIT[\"metre\",1,ID[\"EPSG\",9001]],ID[\"EPSG\",22719]]","proj4":"+proj=utm +zone=19 +ellps=GRS80 +units=m +no_defs +type=crs","bbox":[84,-72,40.8,-66],"unit":"metre","accuracy":null},"24719":{"code":"24719","kind":"CRS-PROJCRS","name":"La Canoa / UTM zone 19N","wkt":"PROJCRS[\"La Canoa / UTM zone 19N\",BASEGEOGCRS[\"La Canoa\",DATUM[\"La Canoa\",ELLIPSOID[\"International 1924\",6378388,297,LENGTHUNIT[\"metre\",1,ID[\"EPSG\",9001]],ID[\"EPSG\",7022]],ID[\"EPSG\",6247]],ID[\"EPSG\",4247]],CONVERSION[\"UTM zone 19N\",METHOD[\"Transverse Mercator\",ID[\"EPSG\",9807]],PARAMETER[\"Latitude of natural origin\",0,ANGLEUNIT[\"degree\",0.0174532925199433,ID[\"EPSG\",9102]],ID[\"EPSG\",8801]],PARAMETER[\"Longitude of natural origin\",-69,ANGLEUNIT[\"degree\",0.0174532925199433,ID[\"EPSG\",9102]],ID[\"EPSG\",8802]],PARAMETER[\"Scale factor at natural origin\",0.9996,SCALEUNIT[\"unity\",1,ID[\"EPSG\",9201]],ID[\"EPSG\",8805]],PARAMETER[\"False easting\",500000,LENGTHUNIT[\"metre\",1,ID[\"EPSG\",9001]],ID[\"EPSG\",8806]],PARAMETER[\"False northing\",0,LENGTHUNIT[\"metre\",1,ID[\"EPSG\",9001]],ID[\"EPSG\",8807]],ID[\"EPSG\",16019]],CS[Cartesian,2,ID[\"EPSG\",4400]],AXIS[\"Easting (E)\",east],AXIS[\"Northing (N)\",north],LENGTHUNIT[\"metre\",1,ID[\"EPSG\",9001]],ID[\"EPSG\",24719]]","proj4":"+proj=utm +zone=19 +ellps=intl +towgs84=-270.933,115.599,-360.226,-5.266,-1.238,2.381,-5.109 +units=m +no_defs +type=crs","bbox":[12.25,-72,0.73,-66],"unit":"metre","accuracy":15},"26719":{"code":"26719","kind":"CRS-PROJCRS","name":"NAD27 / UTM zone 19N","wkt":"PROJCRS[\"NAD27 / UTM zone 19N\",BASEGEOGCRS[\"NAD27\",DATUM[\"North American Datum 1927\",ELLIPSOID[\"Clarke 1866\",6378206.4,294.978698213901,LENGTHUNIT[\"metre\",1,ID[\"EPSG\",9001]],ID[\"EPSG\",7008]],ID[\"EPSG\",6267]],ID[\"EPSG\",4267]],CONVERSION[\"UTM zone 19N\",METHOD[\"Transverse Mercator\",ID[\"EPSG\",9807]],PARAMETER[\"Latitude of natural origin\",0,ANGLEUNIT[\"degree\",0.0174532925199433,ID[\"EPSG\",9102]],ID[\"EPSG\",8801]],PARAMETER[\"Longitude of natural origin\",-69,ANGLEUNIT[\"degree\",0.0174532925199433,ID[\"EPSG\",9102]],ID[\"EPSG\",8802]],PARAMETER[\"Scale factor at natural origin\",0.9996,SCALEUNIT[\"unity\",1,ID[\"EPSG\",9201]],ID[\"EPSG\",8805]],PARAMETER[\"False easting\",500000,LENGTHUNIT[\"metre\",1,ID[\"EPSG\",9001]],ID[\"EPSG\",8806]],PARAMETER[\"False northing\",0,LENGTHUNIT[\"metre\",1,ID[\"EPSG\",9001]],ID[\"EPSG\",8807]],ID[\"EPSG\",16019]],CS[Cartesian,2,ID[\"EPSG\",4400]],AXIS[\"Easting (E)\",east],AXIS[\"Northing (N)\",north],LENGTHUNIT[\"metre\",1,ID[\"EPSG\",9001]],ID[\"EPSG\",26719]]","proj4":"+proj=utm +zone=19 +ellps=clrk66 +nadgrids=NTv2_0.gsb +units=m +no_defs +type=crs","bbox":[83.17,-72,33.61,-66],"unit":"metre","accuracy":2},"32719":{"code":"32719","kind":"CRS-PROJCRS","name":"WGS 84 / UTM zone 19S","wkt":"PROJCRS[\"WGS 84 / UTM zone 19S\",BASEGEOGCRS[\"WGS 84\",ENSEMBLE[\"World Geodetic System 1984 ensemble\", MEMBER[\"World Geodetic System 1984 (Transit)\", ID[\"EPSG\",1166]], MEMBER[\"World Geodetic System 1984 (G730)\", ID[\"EPSG\",1152]], MEMBER[\"World Geodetic System 1984 (G873)\", ID[\"EPSG\",1153]], MEMBER[\"World Geodetic System 1984 (G1150)\", ID[\"EPSG\",1154]], MEMBER[\"World Geodetic System 1984 (G1674)\", ID[\"EPSG\",1155]], MEMBER[\"World Geodetic System 1984 (G1762)\", ID[\"EPSG\",1156]], MEMBER[\"World Geodetic System 1984 (G2139)\", ID[\"EPSG\",1309]], MEMBER[\"World Geodetic System 1984 (G2296)\", ID[\"EPSG\",1383]], ELLIPSOID[\"WGS 84\",6378137,298.257223563,LENGTHUNIT[\"metre\",1,ID[\"EPSG\",9001]],ID[\"EPSG\",7030]], ENSEMBLEACCURACY[2],ID[\"EPSG\",6326]],ID[\"EPSG\",4326]],CONVERSION[\"UTM zone 19S\",METHOD[\"Transverse Mercator\",ID[\"EPSG\",9807]],PARAMETER[\"Latitude of natural origin\",0,ANGLEUNIT[\"degree\",0.0174532925199433,ID[\"EPSG\",9102]],ID[\"EPSG\",8801]],PARAMETER[\"Longitude of natural origin\",-69,ANGLEUNIT[\"degree\",0.0174532925199433,ID[\"EPSG\",9102]],ID[\"EPSG\",8802]],PARAMETER[\"Scale factor at natural origin\",0.9996,SCALEUNIT[\"unity\",1,ID[\"EPSG\",9201]],ID[\"EPSG\",8805]],PARAMETER[\"False easting\",500000,LENGTHUNIT[\"metre\",1,ID[\"EPSG\",9001]],ID[\"EPSG\",8806]],PARAMETER[\"False northing\",10000000,LENGTHUNIT[\"metre\",1,ID[\"EPSG\",9001]],ID[\"EPSG\",8807]],ID[\"EPSG\",16119]],CS[Cartesian,2,ID[\"EPSG\",4400]],AXIS[\"Easting (E)\",east],AXIS[\"Northing (N)\",north],LENGTHUNIT[\"metre\",1,ID[\"EPSG\",9001]],ID[\"EPSG\",32719]]","proj4":"+proj=utm +zone=19 +south +datum=WGS84 +units=m +no_defs +type=crs","bbox":[0,-72,-80,-66],"unit":"metre","accuracy":null},"102719":{"accuracy":"","authority":"ESRI","bbox":[36.59,-84.33,33.83,-75.38],"code":"102719","default_trans":0,"kind":"CRS-PROJCRS","name":"NAD 1983 SPCS North Carolina (Feet)","proj4":"+proj=lcc +lat_0=33.75 +lon_0=-79 +lat_1=34.3333333333333 +lat_2=36.1666666666667 +x_0=609601.220000001 +y_0=0 +datum=NAD83 +units=us-ft +no_defs +type=crs","trans":[],"unit":"","wkt":"PROJCS[\"NAD_1983_StatePlane_North_Carolina_FIPS_3200_Feet (deprecated)\",GEOGCS[\"NAD83\",DATUM[\"North_American_Datum_1983\",SPHEROID[\"GRS 1980\",6378137,298.257222101,AUTHORITY[\"EPSG\",\"7019\"]],AUTHORITY[\"EPSG\",\"6269\"]],PRIMEM[\"Greenwich\",0,AUTHORITY[\"EPSG\",\"8901\"]],UNIT[\"degree\",0.0174532925199433,AUTHORITY[\"EPSG\",\"9122\"]],AUTHORITY[\"EPSG\",\"4269\"]],PROJECTION[\"Lambert_Conformal_Conic_2SP\"],PARAMETER[\"latitude_of_origin\",33.75],PARAMETER[\"central_meridian\",-79],PARAMETER[\"standard_parallel_1\",34.3333333333333],PARAMETER[\"standard_parallel_2\",36.1666666666667],PARAMETER[\"false_easting\",2000000.00261667],PARAMETER[\"false_northing\",0],UNIT[\"US survey foot\",0.304800609601219,AUTHORITY[\"EPSG\",\"9003\"]],AXIS[\"Easting\",EAST],AXIS[\"Northing\",NORTH],AUTHORITY[\"ESRI\",\"102719\"]]"},"103719":{"code":"103719","kind":"CRS-PROJCRS","name":"NAD 1983 HARN Adj. Minnesota Cass South (US foot)","wkt":"PROJCS[\"NAD_1983_HARN_Adj_MN_Cass_South_Feet\",GEOGCS[\"GCS_NAD_1983_HARN_Adj_MN_Cass_South\",DATUM[\"D_NAD_1983_HARN_Adj_MN_Cass_South\",SPHEROID[\"S_GRS_1980_Adj_MN_Cass_South\",6378546.957,298.257222100883,AUTHORITY[\"ESRI\",\"107711\"]],AUTHORITY[\"ESRI\",\"106711\"]],PRIMEM[\"Greenwich\",0,AUTHORITY[\"EPSG\",\"8901\"]],UNIT[\"degree\",0.0174532925199433,AUTHORITY[\"EPSG\",\"9122\"]],AUTHORITY[\"ESRI\",\"104711\"]],PROJECTION[\"Lambert_Conformal_Conic_2SP\"],PARAMETER[\"latitude_of_origin\",46.1563888888889],PARAMETER[\"central_meridian\",-94.4666666666667],PARAMETER[\"standard_parallel_1\",46.2666666666667],PARAMETER[\"standard_parallel_2\",46.7333333333333],PARAMETER[\"false_easting\",500000],PARAMETER[\"false_northing\",100000],UNIT[\"US survey foot\",0.304800609601219,AUTHORITY[\"EPSG\",\"9003\"]],AXIS[\"Easting\",EAST],AXIS[\"Northing\",NORTH],AUTHORITY[\"ESRI\",\"103719\"]]","proj4":"+proj=lcc +lat_0=46.1563888888889 +lon_0=-94.4666666666667 +lat_1=46.2666666666667 +lat_2=46.7333333333333 +x_0=152400.30480061 +y_0=30480.0609601219 +a=6378546.957 +rf=298.257222100883 +units=us-ft +no_defs +type=crs","bbox":[49.38,-97.22,43.49,-89.49],"unit":null,"accuracy":null},"104719":{"code":"104719","kind":"CRS-GEOGCRS","name":"NAD 1983 HARN Adj. Minnesota Dodge","wkt":"GEOGCS[\"GCS_NAD_1983_HARN_Adj_MN_Dodge\",DATUM[\"D_NAD_1983_HARN_Adj_MN_Dodge\",SPHEROID[\"S_GRS_1980_Adj_MN_Dodge\",6378481.425,298.257222100883,AUTHORITY[\"ESRI\",\"107719\"]],AUTHORITY[\"ESRI\",\"106719\"]],PRIMEM[\"Greenwich\",0,AUTHORITY[\"EPSG\",\"8901\"]],UNIT[\"degree\",0.0174532925199433,AUTHORITY[\"EPSG\",\"9122\"]],AUTHORITY[\"ESRI\",\"104719\"]]","proj4":"+proj=longlat +a=6378481.425 +rf=298.257222100883 +no_defs +type=crs","bbox":[49.38,-97.22,43.49,-89.49],"unit":null,"accuracy":null}}