{"2789":{"code":"2789","kind":"CRS-PROJCRS","name":"NAD83(HARN) / Idaho West","wkt":"PROJCRS[\"NAD83(HARN) / Idaho West\",BASEGEOGCRS[\"NAD83(HARN)\",DATUM[\"NAD83 (High Accuracy Reference Network)\",ELLIPSOID[\"GRS 1980\",6378137,298.257222101,LENGTHUNIT[\"metre\",1,ID[\"EPSG\",9001]],ID[\"EPSG\",7019]],ID[\"EPSG\",6152]],ID[\"EPSG\",4152]],CONVERSION[\"SPCS83 Idaho West zone (meter)\",METHOD[\"Transverse Mercator\",ID[\"EPSG\",9807]],PARAMETER[\"Latitude of natural origin\",41.6666666666669,ANGLEUNIT[\"degree\",0.0174532925199433,ID[\"EPSG\",9102]],ID[\"EPSG\",8801]],PARAMETER[\"Longitude of natural origin\",-115.75,ANGLEUNIT[\"degree\",0.0174532925199433,ID[\"EPSG\",9102]],ID[\"EPSG\",8802]],PARAMETER[\"Scale factor at natural origin\",0.999933333,SCALEUNIT[\"unity\",1,ID[\"EPSG\",9201]],ID[\"EPSG\",8805]],PARAMETER[\"False easting\",800000,LENGTHUNIT[\"metre\",1,ID[\"EPSG\",9001]],ID[\"EPSG\",8806]],PARAMETER[\"False northing\",0,LENGTHUNIT[\"metre\",1,ID[\"EPSG\",9001]],ID[\"EPSG\",8807]],ID[\"EPSG\",11133]],CS[Cartesian,2,ID[\"EPSG\",4499]],AXIS[\"Easting (X)\",east],AXIS[\"Northing (Y)\",north],LENGTHUNIT[\"metre\",1,ID[\"EPSG\",9001]],ID[\"EPSG\",2789]]","proj4":"+proj=tmerc +lat_0=41.6666666666667 +lon_0=-115.75 +k=0.999933333 +x_0=800000 +y_0=0 +ellps=GRS80 +towgs84=0,0,0,0,0,0,0 +units=m +no_defs +type=crs","bbox":[49.01,-117.24,41.99,-114.32],"unit":"metre","accuracy":2},"3789":{"code":"3789","kind":"CRS-PROJCRS","name":"NZGD2000 / Campbell Island TM 2000","wkt":"PROJCRS[\"NZGD2000 / Campbell Island TM 2000\",BASEGEOGCRS[\"NZGD2000\",DATUM[\"New Zealand Geodetic Datum 2000\",ELLIPSOID[\"GRS 1980\",6378137,298.257222101,LENGTHUNIT[\"metre\",1,ID[\"EPSG\",9001]],ID[\"EPSG\",7019]],ID[\"EPSG\",6167]],ID[\"EPSG\",4167]],CONVERSION[\"Campbell Island Transverse Mercator 2000\",METHOD[\"Transverse Mercator\",ID[\"EPSG\",9807]],PARAMETER[\"Latitude of natural origin\",0,ANGLEUNIT[\"degree\",0.0174532925199433,ID[\"EPSG\",9102]],ID[\"EPSG\",8801]],PARAMETER[\"Longitude of natural origin\",169,ANGLEUNIT[\"degree\",0.0174532925199433,ID[\"EPSG\",9102]],ID[\"EPSG\",8802]],PARAMETER[\"Scale factor at natural origin\",1,SCALEUNIT[\"unity\",1,ID[\"EPSG\",9201]],ID[\"EPSG\",8805]],PARAMETER[\"False easting\",3500000,LENGTHUNIT[\"metre\",1,ID[\"EPSG\",9001]],ID[\"EPSG\",8806]],PARAMETER[\"False northing\",10000000,LENGTHUNIT[\"metre\",1,ID[\"EPSG\",9001]],ID[\"EPSG\",8807]],ID[\"EPSG\",17961]],CS[Cartesian,2,ID[\"EPSG\",4500]],AXIS[\"Northing (N)\",north],AXIS[\"Easting (E)\",east],LENGTHUNIT[\"metre\",1,ID[\"EPSG\",9001]],ID[\"EPSG\",3789]]","proj4":"+proj=tmerc +lat_0=0 +lon_0=169 +k=1 +x_0=3500000 +y_0=10000000 +ellps=GRS80 +towgs84=0,0,0,0,0,0,0 +units=m +no_defs +type=crs +axis=neu","bbox":[-52.26,168.65,-52.83,169.6],"unit":"metre","accuracy":1},"4789":{"code":"4789","kind":"CRS-PROJCRS","name":"New Beijing / 3-degree Gauss-Kruger CM 96E","wkt":"PROJCRS[\"New Beijing / 3-degree Gauss-Kruger CM 96E\",BASEGEOGCRS[\"New Beijing\",DATUM[\"New Beijing\",ELLIPSOID[\"Krassowsky 1940\",6378245,298.3,LENGTHUNIT[\"metre\",1,ID[\"EPSG\",9001]],ID[\"EPSG\",7024]],ID[\"EPSG\",1045]],ID[\"EPSG\",4555]],CONVERSION[\"3-degree Gauss-Kruger CM 96E\",METHOD[\"Transverse Mercator\",ID[\"EPSG\",9807]],PARAMETER[\"Latitude of natural origin\",0,ANGLEUNIT[\"degree\",0.0174532925199433,ID[\"EPSG\",9102]],ID[\"EPSG\",8801]],PARAMETER[\"Longitude of natural origin\",96,ANGLEUNIT[\"degree\",0.0174532925199433,ID[\"EPSG\",9102]],ID[\"EPSG\",8802]],PARAMETER[\"Scale factor at natural origin\",1,SCALEUNIT[\"unity\",1,ID[\"EPSG\",9201]],ID[\"EPSG\",8805]],PARAMETER[\"False easting\",500000,LENGTHUNIT[\"metre\",1,ID[\"EPSG\",9001]],ID[\"EPSG\",8806]],PARAMETER[\"False northing\",0,LENGTHUNIT[\"metre\",1,ID[\"EPSG\",9001]],ID[\"EPSG\",8807]],ID[\"EPSG\",16392]],CS[Cartesian,2,ID[\"EPSG\",4530]],AXIS[\"Northing (X)\",north],AXIS[\"Easting (Y)\",east],LENGTHUNIT[\"metre\",1,ID[\"EPSG\",9001]],ID[\"EPSG\",4789]]","proj4":"+proj=tmerc +lat_0=0 +lon_0=96 +k=1 +x_0=500000 +y_0=0 +ellps=krass +units=m +no_defs +type=crs +axis=neu","bbox":[44.5,94.5,28.23,97.51],"unit":"metre","accuracy":null},"5789":{"code":"5789","kind":"CRS-VERTCRS","name":"KOC WD depth","wkt":"VERTCRS[\"KOC WD depth\",BASEVERTCRS[\"KOC WD height\",VDATUM[\"KOC Well Datum\",ID[\"EPSG\",5187]],ID[\"EPSG\",7979]],DERIVINGCONVERSION[\"Height <> Depth Conversion\",METHOD[\"Height Depth Reversal\",ID[\"EPSG\",1068]],ID[\"EPSG\",7812]],CS[vertical,1,ID[\"EPSG\",6498]],AXIS[\"Depth (D)\",down],LENGTHUNIT[\"metre\",1,ID[\"EPSG\",9001]],ID[\"EPSG\",5789]]","proj4":"+vunits=m +no_defs +type=crs","bbox":[30.09,46.54,28.53,48.48],"unit":"metre","accuracy":null},"6789":{"code":"6789","kind":"CRS-PROJCRS","name":"NAD83(CORS96) / Oregon Bend-Klamath Falls zone (ft)","wkt":"PROJCRS[\"NAD83(CORS96) / Oregon Bend-Klamath Falls zone (ft)\",BASEGEOGCRS[\"NAD83(CORS96)\",DATUM[\"NAD83 (Continuously Operating Reference Station 1996)\",ELLIPSOID[\"GRS 1980\",6378137,298.257222101,LENGTHUNIT[\"metre\",1,ID[\"EPSG\",9001]],ID[\"EPSG\",7019]],ID[\"EPSG\",1133]],ID[\"EPSG\",6783]],CONVERSION[\"Oregon Bend-Klamath Falls zone (international foot)\",METHOD[\"Transverse Mercator\",ID[\"EPSG\",9807]],PARAMETER[\"Latitude of natural origin\",41.7500000000003,ANGLEUNIT[\"degree\",0.0174532925199433,ID[\"EPSG\",9102]],ID[\"EPSG\",8801]],PARAMETER[\"Longitude of natural origin\",-121.75,ANGLEUNIT[\"degree\",0.0174532925199433,ID[\"EPSG\",9102]],ID[\"EPSG\",8802]],PARAMETER[\"Scale factor at natural origin\",1.0002,SCALEUNIT[\"unity\",1,ID[\"EPSG\",9201]],ID[\"EPSG\",8805]],PARAMETER[\"False easting\",262467.1916,LENGTHUNIT[\"foot\",0.3048,ID[\"EPSG\",9002]],ID[\"EPSG\",8806]],PARAMETER[\"False northing\",0,LENGTHUNIT[\"foot\",0.3048,ID[\"EPSG\",9002]],ID[\"EPSG\",8807]],ID[\"EPSG\",6744]],CS[Cartesian,2,ID[\"EPSG\",4495]],AXIS[\"Easting (X)\",east],AXIS[\"Northing (Y)\",north],LENGTHUNIT[\"foot\",0.3048,ID[\"EPSG\",9002]],ID[\"EPSG\",6789]]","proj4":"+proj=tmerc +lat_0=41.75 +lon_0=-121.75 +k=1.0002 +x_0=79999.99999968 +y_0=0 +ellps=GRS80 +units=ft +no_defs +type=crs","bbox":[43.89,-122.45,41.88,-120.77],"unit":"foot","accuracy":null},"7789":{"code":"7789","kind":"CRS-GCENCRS","name":"ITRF2014","wkt":"GEODCRS[\"ITRF2014\", DYNAMIC[FRAMEEPOCH[2010.0]],DATUM[\"International Terrestrial Reference Frame 2014\",ELLIPSOID[\"GRS 1980\",6378137,298.257222101,LENGTHUNIT[\"metre\",1,ID[\"EPSG\",9001]],ID[\"EPSG\",7019]],ID[\"EPSG\",1165]],CS[Cartesian,3,ID[\"EPSG\",6500]],AXIS[\"Geocentric X (X)\",geocentricX,LENGTHUNIT[\"metre\",1,ID[\"EPSG\",9001]]],AXIS[\"Geocentric Y (Y)\",geocentricY,LENGTHUNIT[\"metre\",1,ID[\"EPSG\",9001]]],AXIS[\"Geocentric Z (Z)\",geocentricZ,LENGTHUNIT[\"metre\",1,ID[\"EPSG\",9001]]],ID[\"EPSG\",7789]]","proj4":"+proj=geocent +ellps=GRS80 +units=m +no_defs +type=crs","bbox":[90,-180,-90,180],"unit":"metre","accuracy":null},"8789":{"code":"8789","kind":"CRS-COMPOUNDCRS","name":"NAD83 / Virginia South (ftUS) + NAVD88 height (ftUS)","wkt":"COMPOUNDCRS[\"NAD83 / Virginia South (ftUS) + NAVD88 height (ftUS)\",PROJCRS[\"NAD83 / Virginia South (ftUS)\",BASEGEOGCRS[\"NAD83\",DATUM[\"North American Datum 1983\",ELLIPSOID[\"GRS 1980\",6378137,298.257222101,LENGTHUNIT[\"metre\",1,ID[\"EPSG\",9001]],ID[\"EPSG\",7019]],ID[\"EPSG\",6269]],ID[\"EPSG\",4269]],CONVERSION[\"SPCS83 Virginia South zone (US survey foot)\",METHOD[\"Lambert Conic Conformal (2SP)\",ID[\"EPSG\",9802]],PARAMETER[\"Latitude of false origin\",36.3333333333336,ANGLEUNIT[\"degree\",0.0174532925199433,ID[\"EPSG\",9102]],ID[\"EPSG\",8821]],PARAMETER[\"Longitude of false origin\",-78.5000000000003,ANGLEUNIT[\"degree\",0.0174532925199433,ID[\"EPSG\",9102]],ID[\"EPSG\",8822]],PARAMETER[\"Latitude of 1st standard parallel\",37.9666666666669,ANGLEUNIT[\"degree\",0.0174532925199433,ID[\"EPSG\",9102]],ID[\"EPSG\",8823]],PARAMETER[\"Latitude of 2nd standard parallel\",36.7666666666669,ANGLEUNIT[\"degree\",0.0174532925199433,ID[\"EPSG\",9102]],ID[\"EPSG\",8824]],PARAMETER[\"Easting at false origin\",11482916.667,LENGTHUNIT[\"US survey foot\",0.304800609601219,ID[\"EPSG\",9003]],ID[\"EPSG\",8826]],PARAMETER[\"Northing at false origin\",3280833.333,LENGTHUNIT[\"US survey foot\",0.304800609601219,ID[\"EPSG\",9003]],ID[\"EPSG\",8827]],ID[\"EPSG\",15366]],CS[Cartesian,2,ID[\"EPSG\",4497]],AXIS[\"Easting (X)\",east],AXIS[\"Northing (Y)\",north],LENGTHUNIT[\"US survey foot\",0.304800609601219,ID[\"EPSG\",9003]],ID[\"EPSG\",2284]],VERTCRS[\"NAVD88 height (ftUS)\",BASEVERTCRS[\"NAVD88 height\",VDATUM[\"North American Vertical Datum 1988\",ID[\"EPSG\",5103]],ID[\"EPSG\",5703]],DERIVINGCONVERSION[\"Vertical Axis Unit Conversion\",METHOD[\"Change of Vertical Unit\",ID[\"EPSG\",1104]],ID[\"EPSG\",7813]],CS[vertical,1,ID[\"EPSG\",6497]],AXIS[\"Gravity-related height (H)\",up],LENGTHUNIT[\"US survey foot\",0.304800609601219,ID[\"EPSG\",9003]],ID[\"EPSG\",6360]],ID[\"EPSG\",8789]]","proj4":"+proj=lcc +lat_0=36.3333333333333 +lon_0=-78.5 +lat_1=37.9666666666667 +lat_2=36.7666666666667 +x_0=3500000.0001016 +y_0=999999.9998984 +datum=NAD83 +units=us-ft +vunits=us-ft +no_defs +type=crs","bbox":[38.28,-83.68,36.54,-75.31],"unit":null,"accuracy":null},"26789":{"code":"26789","kind":"CRS-PROJCRS","name":"NAD 1927 SPCS Zone Michigan Central","wkt":"PROJCS[\"NAD_1927_StatePlane_Michigan_Central_FIPS_2112\",GEOGCS[\"NAD27\",DATUM[\"North_American_Datum_1927\",SPHEROID[\"Clarke 1866\",6378206.4,294.978698213898,AUTHORITY[\"EPSG\",\"7008\"]],AUTHORITY[\"EPSG\",\"6267\"]],PRIMEM[\"Greenwich\",0,AUTHORITY[\"EPSG\",\"8901\"]],UNIT[\"degree\",0.0174532925199433,AUTHORITY[\"EPSG\",\"9122\"]],AUTHORITY[\"EPSG\",\"4267\"]],PROJECTION[\"Lambert_Conformal_Conic_2SP\"],PARAMETER[\"latitude_of_origin\",43.3166666666667],PARAMETER[\"central_meridian\",-84.3333333333333],PARAMETER[\"standard_parallel_1\",44.1833333333333],PARAMETER[\"standard_parallel_2\",45.7],PARAMETER[\"false_easting\",2000000],PARAMETER[\"false_northing\",0],UNIT[\"US survey foot\",0.304800609601219,AUTHORITY[\"EPSG\",\"9003\"]],AXIS[\"Easting\",EAST],AXIS[\"Northing\",NORTH],AUTHORITY[\"ESRI\",\"26789\"]]","proj4":"+proj=lcc +lat_0=43.3166666666667 +lon_0=-84.3333333333333 +lat_1=44.1833333333333 +lat_2=45.7 +x_0=609601.219202438 +y_0=0 +datum=NAD27 +units=us-ft +no_defs +type=crs","bbox":[45.92,-87.06,43.8,-82.27],"unit":null,"accuracy":null},"102789":{"accuracy":"","authority":"ESRI","bbox":[1.65,-77.16666666666667,0.6333333333333333,-76.15],"code":"102789","default_trans":0,"kind":"CRS-PROJCRS","name":"MAGNA Mocoa Putumayo 2011","proj4":"+proj=col_urban +lat_0=1.14002335833333 +lon_0=-76.6510212194444 +x_0=1047467.388 +y_0=617828.474 +h_0=655.2 +ellps=GRS80 +units=m +no_defs +type=crs","trans":[],"unit":"","wkt":""},"103789":{"code":"103789","kind":"CRS-PROJCRS","name":"NAD 1983 HARN Adj. Minnesota Waseca (US foot)","wkt":"PROJCS[\"NAD_1983_HARN_Adj_MN_Waseca_Feet\",GEOGCS[\"GCS_NAD_1983_HARN_Adj_MN_Waseca\",DATUM[\"D_NAD_1983_HARN_Adj_MN_Waseca\",SPHEROID[\"S_GRS_1980_Adj_MN_Waseca\",6378481.425,298.257222100883,AUTHORITY[\"ESRI\",\"107781\"]],AUTHORITY[\"ESRI\",\"106781\"]],PRIMEM[\"Greenwich\",0,AUTHORITY[\"EPSG\",\"8901\"]],UNIT[\"degree\",0.0174532925199433,AUTHORITY[\"EPSG\",\"9122\"]],AUTHORITY[\"ESRI\",\"104781\"]],PROJECTION[\"Lambert_Conformal_Conic_2SP\"],PARAMETER[\"latitude_of_origin\",43.8338888888889],PARAMETER[\"central_meridian\",-92.9166666666667],PARAMETER[\"standard_parallel_1\",43.8833333333333],PARAMETER[\"standard_parallel_2\",44.1333333333333],PARAMETER[\"false_easting\",500000],PARAMETER[\"false_northing\",100000],UNIT[\"US survey foot\",0.304800609601219,AUTHORITY[\"EPSG\",\"9003\"]],AXIS[\"Easting\",EAST],AXIS[\"Northing\",NORTH],AUTHORITY[\"ESRI\",\"103789\"]]","proj4":"+proj=lcc +lat_0=43.8338888888889 +lon_0=-92.9166666666667 +lat_1=43.8833333333333 +lat_2=44.1333333333333 +x_0=152400.30480061 +y_0=30480.0609601219 +a=6378481.425 +rf=298.257222100883 +units=us-ft +no_defs +type=crs","bbox":[49.38,-97.22,43.49,-89.49],"unit":null,"accuracy":null}}