{"2908":{"code":"2908","kind":"CRS-PROJCRS","name":"NAD83(HARN) / New York Long Island (ftUS)","wkt":"PROJCRS[\"NAD83(HARN) / New York Long Island (ftUS)\",BASEGEOGCRS[\"NAD83(HARN)\",DATUM[\"NAD83 (High Accuracy Reference Network)\",ELLIPSOID[\"GRS 1980\",6378137,298.257222101,LENGTHUNIT[\"metre\",1,ID[\"EPSG\",9001]],ID[\"EPSG\",7019]],ID[\"EPSG\",6152]],ID[\"EPSG\",4152]],CONVERSION[\"SPCS83 New York Long Island zone (US survey foot)\",METHOD[\"Lambert Conic Conformal (2SP)\",ID[\"EPSG\",9802]],PARAMETER[\"Latitude of false origin\",40.1666666666669,ANGLEUNIT[\"degree\",0.0174532925199433,ID[\"EPSG\",9102]],ID[\"EPSG\",8821]],PARAMETER[\"Longitude of false origin\",-74,ANGLEUNIT[\"degree\",0.0174532925199433,ID[\"EPSG\",9102]],ID[\"EPSG\",8822]],PARAMETER[\"Latitude of 1st standard parallel\",41.0333333333336,ANGLEUNIT[\"degree\",0.0174532925199433,ID[\"EPSG\",9102]],ID[\"EPSG\",8823]],PARAMETER[\"Latitude of 2nd standard parallel\",40.6666666666669,ANGLEUNIT[\"degree\",0.0174532925199433,ID[\"EPSG\",9102]],ID[\"EPSG\",8824]],PARAMETER[\"Easting at false origin\",984250,LENGTHUNIT[\"US survey foot\",0.304800609601219,ID[\"EPSG\",9003]],ID[\"EPSG\",8826]],PARAMETER[\"Northing at false origin\",0,LENGTHUNIT[\"US survey foot\",0.304800609601219,ID[\"EPSG\",9003]],ID[\"EPSG\",8827]],ID[\"EPSG\",15345]],CS[Cartesian,2,ID[\"EPSG\",4497]],AXIS[\"Easting (X)\",east],AXIS[\"Northing (Y)\",north],LENGTHUNIT[\"US survey foot\",0.304800609601219,ID[\"EPSG\",9003]],ID[\"EPSG\",2908]]","proj4":"+proj=lcc +lat_0=40.1666666666667 +lon_0=-74 +lat_1=41.0333333333333 +lat_2=40.6666666666667 +x_0=300000 +y_0=0 +ellps=GRS80 +towgs84=0,0,0,0,0,0,0 +units=us-ft +no_defs +type=crs","bbox":[41.3,-74.26,40.47,-71.8],"unit":"US survey foot","accuracy":2},"3908":{"accuracy":5,"authority":"EPSG","bbox":[46.55,16.5,41.79,19.51],"code":"3908","default_trans":3962,"kind":"CRS-PROJCRS","name":"MGI 1901 / Balkans zone 6","proj4":"+proj=tmerc +lat_0=0 +lon_0=18 +k=0.9999 +x_0=6500000 +y_0=0 +ellps=bessel +towgs84=682,-203,480,0,0,0,0 +units=m +no_defs +type=crs","trans":[3914,3915,3916,3917,3918,3919,3921,3922,3923,3924,3925,3926,3927,3928,3962,3963,3964,3965,6205,6206,7675,7676,8680,8681,8688,8689,8823,9142,9143,9486,9495,9496],"unit":"metre","wkt":"PROJCS[\"MGI 1901 / Balkans zone 6\",GEOGCS[\"MGI 1901\",DATUM[\"MGI_1901\",SPHEROID[\"Bessel 1841\",6377397.155,299.1528128],TOWGS84[682,-203,480,0,0,0,0]],PRIMEM[\"Greenwich\",0,AUTHORITY[\"EPSG\",\"8901\"]],UNIT[\"degree\",0.0174532925199433,AUTHORITY[\"EPSG\",\"9122\"]],AUTHORITY[\"EPSG\",\"3906\"]],PROJECTION[\"Transverse_Mercator\"],PARAMETER[\"latitude_of_origin\",0],PARAMETER[\"central_meridian\",18],PARAMETER[\"scale_factor\",0.9999],PARAMETER[\"false_easting\",6500000],PARAMETER[\"false_northing\",0],UNIT[\"metre\",1,AUTHORITY[\"EPSG\",\"9001\"]],AUTHORITY[\"EPSG\",\"3908\"]]"},"4908":{"code":"4908","kind":"CRS-GCENCRS","name":"GR96","wkt":"GEODCRS[\"GR96\",DATUM[\"Greenland 1996\",ELLIPSOID[\"GRS 1980\",6378137,298.257222101,LENGTHUNIT[\"metre\",1,ID[\"EPSG\",9001]],ID[\"EPSG\",7019]],ID[\"EPSG\",6747]],CS[Cartesian,3,ID[\"EPSG\",6500]],AXIS[\"Geocentric X (X)\",geocentricX,LENGTHUNIT[\"metre\",1,ID[\"EPSG\",9001]]],AXIS[\"Geocentric Y (Y)\",geocentricY,LENGTHUNIT[\"metre\",1,ID[\"EPSG\",9001]]],AXIS[\"Geocentric Z (Z)\",geocentricZ,LENGTHUNIT[\"metre\",1,ID[\"EPSG\",9001]]],ID[\"EPSG\",4908]]","proj4":"+proj=geocent +ellps=GRS80 +units=m +no_defs +type=crs","bbox":[87.02,-75,56.38,7.99],"unit":"metre","accuracy":null},"7908":{"code":"7908","kind":"CRS-GEOG3DCRS","name":"ITRF97","wkt":"GEOGCRS[\"ITRF97\", DYNAMIC[FRAMEEPOCH[1997.0]],DATUM[\"International Terrestrial Reference Frame 1997\",ELLIPSOID[\"GRS 1980\",6378137,298.257222101,LENGTHUNIT[\"metre\",1,ID[\"EPSG\",9001]],ID[\"EPSG\",7019]],ID[\"EPSG\",6655]],CS[ellipsoidal,3,ID[\"EPSG\",6423]],AXIS[\"Geodetic latitude (Lat)\",north,ANGLEUNIT[\"degree\",0.0174532925199433,ID[\"EPSG\",9102]]],AXIS[\"Geodetic longitude (Lon)\",east,ANGLEUNIT[\"degree\",0.0174532925199433,ID[\"EPSG\",9102]]],AXIS[\"Ellipsoidal height (h)\",up,LENGTHUNIT[\"metre\",1,ID[\"EPSG\",9001]]],ID[\"EPSG\",7908]]","proj4":"+proj=longlat +ellps=GRS80 +towgs84=-14.63,-27.62,-25.32,-1.7893,-0.6047,0.9962,6.695 +no_defs +type=crs","bbox":[90,-180,-90,180],"unit":"degree (supplier to define representation)","accuracy":0.18},"8908":{"code":"8908","kind":"CRS-PROJCRS","name":"CR-SIRGAS / CRTM05","wkt":"PROJCRS[\"CR-SIRGAS / CRTM05\",BASEGEOGCRS[\"CR-SIRGAS\",DATUM[\"CR-SIRGAS\",ELLIPSOID[\"GRS 1980\",6378137,298.257222101,LENGTHUNIT[\"metre\",1,ID[\"EPSG\",9001]],ID[\"EPSG\",7019]],ID[\"EPSG\",1225]],ID[\"EPSG\",8907]],CONVERSION[\"Costa Rica TM 2005\",METHOD[\"Transverse Mercator\",ID[\"EPSG\",9807]],PARAMETER[\"Latitude of natural origin\",0,ANGLEUNIT[\"degree\",0.0174532925199433,ID[\"EPSG\",9102]],ID[\"EPSG\",8801]],PARAMETER[\"Longitude of natural origin\",-84,ANGLEUNIT[\"degree\",0.0174532925199433,ID[\"EPSG\",9102]],ID[\"EPSG\",8802]],PARAMETER[\"Scale factor at natural origin\",0.9999,SCALEUNIT[\"unity\",1,ID[\"EPSG\",9201]],ID[\"EPSG\",8805]],PARAMETER[\"False easting\",500000,LENGTHUNIT[\"metre\",1,ID[\"EPSG\",9001]],ID[\"EPSG\",8806]],PARAMETER[\"False northing\",0,LENGTHUNIT[\"metre\",1,ID[\"EPSG\",9001]],ID[\"EPSG\",8807]],ID[\"EPSG\",5366]],CS[Cartesian,2,ID[\"EPSG\",4400]],AXIS[\"Easting (E)\",east],AXIS[\"Northing (N)\",north],LENGTHUNIT[\"metre\",1,ID[\"EPSG\",9001]],ID[\"EPSG\",8908]]","proj4":"+proj=tmerc +lat_0=0 +lon_0=-84 +k=0.9999 +x_0=500000 +y_0=0 +ellps=GRS80 +units=m +no_defs +type=crs","bbox":[11.22,-85.97,7.98,-82.53],"unit":"metre","accuracy":null},"20908":{"code":"20908","kind":"CRS-PROJCRS","name":"GSK-2011 / Gauss-Kruger zone 8","wkt":"PROJCRS[\"GSK-2011 / Gauss-Kruger zone 8\",BASEGEOGCRS[\"GSK-2011\",DATUM[\"Geodezicheskaya Sistema Koordinat 2011\",ELLIPSOID[\"GSK-2011\",6378136.5,298.2564151,LENGTHUNIT[\"metre\",1,ID[\"EPSG\",9001]],ID[\"EPSG\",1025]],ID[\"EPSG\",1159]],ID[\"EPSG\",7683]],CONVERSION[\"6-degree Gauss-Kruger zone 8\",METHOD[\"Transverse Mercator\",ID[\"EPSG\",9807]],PARAMETER[\"Latitude of natural origin\",0,ANGLEUNIT[\"degree\",0.0174532925199433,ID[\"EPSG\",9102]],ID[\"EPSG\",8801]],PARAMETER[\"Longitude of natural origin\",45,ANGLEUNIT[\"degree\",0.0174532925199433,ID[\"EPSG\",9102]],ID[\"EPSG\",8802]],PARAMETER[\"Scale factor at natural origin\",1,SCALEUNIT[\"unity\",1,ID[\"EPSG\",9201]],ID[\"EPSG\",8805]],PARAMETER[\"False easting\",8500000,LENGTHUNIT[\"metre\",1,ID[\"EPSG\",9001]],ID[\"EPSG\",8806]],PARAMETER[\"False northing\",0,LENGTHUNIT[\"metre\",1,ID[\"EPSG\",9001]],ID[\"EPSG\",8807]],ID[\"EPSG\",16208]],CS[Cartesian,2,ID[\"EPSG\",4530]],AXIS[\"Northing (X)\",north],AXIS[\"Easting (Y)\",east],LENGTHUNIT[\"metre\",1,ID[\"EPSG\",9001]],ID[\"EPSG\",20908]]","proj4":"+proj=tmerc +lat_0=0 +lon_0=45 +k=1 +x_0=8500000 +y_0=0 +ellps=GSK2011 +towgs84=0,0,0,0,0,0,0 +units=m +no_defs +type=crs +axis=neu","bbox":[80.91,42,41.19,48],"unit":"metre","accuracy":1},"26908":{"code":"26908","kind":"CRS-PROJCRS","name":"NAD83 / UTM zone 8N","wkt":"PROJCRS[\"NAD83 / UTM zone 8N\",BASEGEOGCRS[\"NAD83\",DATUM[\"North American Datum 1983\",ELLIPSOID[\"GRS 1980\",6378137,298.257222101,LENGTHUNIT[\"metre\",1,ID[\"EPSG\",9001]],ID[\"EPSG\",7019]],ID[\"EPSG\",6269]],ID[\"EPSG\",4269]],CONVERSION[\"UTM zone 8N\",METHOD[\"Transverse Mercator\",ID[\"EPSG\",9807]],PARAMETER[\"Latitude of natural origin\",0,ANGLEUNIT[\"degree\",0.0174532925199433,ID[\"EPSG\",9102]],ID[\"EPSG\",8801]],PARAMETER[\"Longitude of natural origin\",-135,ANGLEUNIT[\"degree\",0.0174532925199433,ID[\"EPSG\",9102]],ID[\"EPSG\",8802]],PARAMETER[\"Scale factor at natural origin\",0.9996,SCALEUNIT[\"unity\",1,ID[\"EPSG\",9201]],ID[\"EPSG\",8805]],PARAMETER[\"False easting\",500000,LENGTHUNIT[\"metre\",1,ID[\"EPSG\",9001]],ID[\"EPSG\",8806]],PARAMETER[\"False northing\",0,LENGTHUNIT[\"metre\",1,ID[\"EPSG\",9001]],ID[\"EPSG\",8807]],ID[\"EPSG\",16008]],CS[Cartesian,2,ID[\"EPSG\",4400]],AXIS[\"Easting (E)\",east],AXIS[\"Northing (N)\",north],LENGTHUNIT[\"metre\",1,ID[\"EPSG\",9001]],ID[\"EPSG\",26908]]","proj4":"+proj=utm +zone=8 +ellps=GRS80 +towgs84=0,0,0,0,0,0,0 +units=m +no_defs +type=crs","bbox":[79.42,-138,48.06,-132],"unit":"metre","accuracy":4},"102908":{"code":"102908","kind":"CRS-PROJCRS","name":"NAD 1983 2011 ICS Joliet (US Feet)","wkt":"PROJCS[\"NAD_1983_(2011)_ICS_Joliet_(US_Feet)\",GEOGCS[\"NAD83(2011)\",DATUM[\"NAD83_National_Spatial_Reference_System_2011\",SPHEROID[\"GRS 1980\",6378137,298.257222101,AUTHORITY[\"EPSG\",\"7019\"]],AUTHORITY[\"EPSG\",\"1116\"]],PRIMEM[\"Greenwich\",0,AUTHORITY[\"EPSG\",\"8901\"]],UNIT[\"degree\",0.0174532925199433,AUTHORITY[\"EPSG\",\"9122\"]],AUTHORITY[\"EPSG\",\"6318\"]],PROJECTION[\"Transverse_Mercator\"],PARAMETER[\"latitude_of_origin\",40.55],PARAMETER[\"central_meridian\",-88],PARAMETER[\"scale_factor\",1.000022],PARAMETER[\"false_easting\",8694000],PARAMETER[\"false_northing\",492000],UNIT[\"US survey foot\",0.304800609601219,AUTHORITY[\"EPSG\",\"9003\"]],AXIS[\"Easting\",EAST],AXIS[\"Northing\",NORTH],AUTHORITY[\"ESRI\",\"102908\"]]","proj4":"+proj=tmerc +lat_0=40.55 +lon_0=-88 +k=1.000022 +x_0=2649936.499873 +y_0=149961.8999238 +ellps=GRS80 +units=us-ft +no_defs +type=crs","bbox":[41.73,-88.27,40.99,-87.52],"unit":null,"accuracy":null},"103908":{"accuracy":"","authority":"ESRI","bbox":[47.31,-92.89,42.48,-86.25],"code":"103908","default_trans":0,"kind":"CRS-PROJCRS","name":"NAD 1983 HARN Adj. Wisconsin Door (US foot) (DEPRECATED)","proj4":"+proj=tmerc +lat_0=44.4 +lon_0=-87.2722222222222 +k=0.999991 +x_0=158801.117602235 +y_0=0 +a=6378313.92 +rf=298.26549531037 +units=us-ft +no_defs +type=crs","trans":[],"unit":"","wkt":"PROJCS[\"NAD_1983_HARN_Adj_WI_Door_Feet (deprecated)\",GEOGCS[\"GCS_NAD_1983_HARN_Adj_WI_Door (deprecated)\",DATUM[\"D_NAD_1983_HARN_Adj_WI_DR\",SPHEROID[\"GRS_1980_Adj_WI_DR\",6378313.92,298.26549531037,AUTHORITY[\"ESRI\",\"107811\"]],AUTHORITY[\"ESRI\",\"106811\"]],PRIMEM[\"Greenwich\",0,AUTHORITY[\"EPSG\",\"8901\"]],UNIT[\"degree\",0.0174532925199433,AUTHORITY[\"EPSG\",\"9122\"]],AUTHORITY[\"ESRI\",\"104814\"]],PROJECTION[\"Transverse_Mercator\"],PARAMETER[\"latitude_of_origin\",44.4],PARAMETER[\"central_meridian\",-87.2722222222222],PARAMETER[\"scale_factor\",0.999991],PARAMETER[\"false_easting\",521000],PARAMETER[\"false_northing\",0],UNIT[\"US survey foot\",0.304800609601219,AUTHORITY[\"EPSG\",\"9003\"]],AXIS[\"Easting\",EAST],AXIS[\"Northing\",NORTH],AUTHORITY[\"ESRI\",\"103908\"]]"},"104908":{"code":"104908","kind":"CRS-GEOGCRS","name":"Jupiter","wkt":"GEOGCS[\"GCS_Jupiter_2000\",DATUM[\"D_Jupiter_2000\",SPHEROID[\"Jupiter_2000_IAU_IAG\",71492000,15.4144027598103,AUTHORITY[\"ESRI\",\"107908\"]],AUTHORITY[\"ESRI\",\"106908\"]],PRIMEM[\"Reference_Meridian\",0,AUTHORITY[\"ESRI\",\"108900\"]],UNIT[\"degree\",0.0174532925199433,AUTHORITY[\"EPSG\",\"9122\"]],AUTHORITY[\"ESRI\",\"104908\"]]","proj4":"+proj=longlat +a=71492000 +rf=15.4144027598103 +no_defs +type=crs","bbox":[90,-180,-90,180],"unit":null,"accuracy":null}}